{
  "test_type": "adaptive",
  "grade": 11,
  "count": 41,
  "questions": [
    {
      "ordering_items_ar": [],
      "question_type": "multiple_choice",
      "options_en": [
        "About 30¬∞ and 75¬∞",
        "About 43.8¬∞ and 64.7¬∞",
        "About 20¬∞ and 70¬∞",
        "No two possible angles"
      ],
      "correct_answer": "1",
      "ordering_items_en": [],
      "topic_en": "Vectors and projectiles",
      "explanation_ar": "ўЖўБЎ±Ўґ t = x/(v cosќЄ)=60/(30 cosќЄ)=2/ cosќЄ. ЎЂўЕ y = v sinќЄ t - 1/2 g t^2 вЗТ 30¬Ј(2) tanќЄ - 19.6(1+tan^2ќЄ)=20. Ў®ЎєЎѓ ЎІўДЎ™Ў®Ў≥ўКЎЈ ўЖЎ≠ЎµўД ЎєўДўЙ ўЕЎєЎІЎѓўДЎ© Ў±Ў®ЎІЎєўКЎ© ўБўК tanќЄ Ў™Ў§ЎѓўК Ў•ўДўЙ Ў≠ўДўИўД tanќЄ вЙИ 0.963 ўИ 2.098ЎМ ўИЎІўДЎ≤ўИЎІўКЎІ вЙИ arctan(0.963)вЙИ43.8¬∞ ўИ arctan(2.098)вЙИ64.7¬∞.",
      "test_type": "adaptive",
      "difficulty": "hard",
      "topic_ar": "ЎІўДўЕЎ™ЎђўЗЎІЎ™ ўИЎІўДўЕўВЎ∞ўИўБЎІЎ™",
      "matching_pairs_en": [],
      "question_ar": "ўВЎ∞ўКўБЎ© Ў£ўПЎЈўДўВЎ™ Ў®Ў≥Ў±ЎєЎ© ЎІЎ®Ў™ЎѓЎІЎ¶ўКЎ© 30 m/s. Ў™ўЕЎ± ЎІўДўВЎ∞ўКўБЎ© Ў®ЎІўДўЖўВЎЈЎ© ЎІўДЎ£ўБўВўКЎ© x=60 m ўИЎІўДЎІЎ±Ў™ўБЎІЎє y=20 m ўБўИўВ ўЕЎ≥Ў™ўИўЙ ЎІўДЎІЎЈўДЎІўВ. ўЕЎІ ЎІўДўВўКўЕ ЎІўДЎ™ўВЎ±ўКЎ®ўКЎ© ўДўДЎ≤ЎІўИўКЎ™ўКўЖ ЎІўДўЕўЕўГўЖЎ™ўКўЖ ўДўДЎ•ЎЈўДЎІўВЎЯ (g=9.8 m/s^2)",
      "explanation_en": "Set t = x/(v cosќЄ)=60/(30 cosќЄ)=2/ cosќЄ. Then y = v sinќЄ t - 1/2 g t^2 вЗТ 30¬Ј2 tanќЄ -19.6(1+tan^2ќЄ)=20. Solving yields tanќЄ вЙИ0.963 and 2.098, so ќЄ вЙИ arctan(0.963)вЙИ43.8¬∞ and ќЄ вЙИ arctan(2.098)вЙИ64.7¬∞.",
      "classify_categories_ar": [],
      "classify_items_en": [],
      "grade": 11,
      "matching_pairs_ar": [],
      "question_en": "A projectile is launched at initial speed 30 m/s. It passes through the point x=60 m, y=20 m above launch level. What are the approximate two possible launch angles? (g=9.8 m/s^2)",
      "classify_categories_en": [],
      "classify_items_ar": [],
      "options_ar": [
        "Ў≠ўИЎІўДўК 30¬∞ ўИ 75¬∞",
        "Ў≠ўИЎІўДўК 43.8¬∞ ўИ 64.7¬∞",
        "Ў≠ўИЎІўДўК 20¬∞ ўИ 70¬∞",
        "ўДЎІ Ў™ўИЎђЎѓ Ў≤ЎІўИўКЎ™ЎІўЖ ўЕўЕўГўЖЎ™ЎІўЖ"
      ],
      "id": "6a4a009c91ae4df21ea3969b",
      "created_date": "2026-07-05T06:58:36.341000",
      "updated_date": "2026-07-05T06:58:36.341000",
      "created_by_id": "service_54c00eed-6486-4029-9a2e-cf5b715d0b73",
      "is_sample": false
    },
    {
      "ordering_items_ar": [],
      "question_type": "multiple_choice",
      "options_en": [
        "It has six single CвАУC bonds only",
        "The CвАУC bonds alternate perfectly between single and double",
        "All CвАУC bonds are equal and of intermediate length due to electron delocalization",
        "The central atom is sp hybridized"
      ],
      "correct_answer": "2",
      "ordering_items_en": [],
      "topic_en": "Molecular chemistry",
      "explanation_ar": "Ў®ўЖЎ≤ўКўЖ ўКЎ™ўЕЎ™Ўє Ў®Ў™ЎіЎІЎ±ўГ ѕА ЎѓўДўПўИўГЎІўД (resonance) ўКЎђЎєўД ЎђўЕўКЎє Ў±ўИЎІЎ®ЎЈ CвАУC ўЕЎ™Ў≥ЎІўИўКЎ© Ў®ЎЈўИўД ўЕЎ™ўИЎ≥ЎЈ Ў®ўКўЖ Ў£Ў≠ЎІЎѓўК ўИЎЂўЖЎІЎ¶ўКЎЫ ўЗЎ∞ЎІ ўКўБЎ≥Ў± ЎІЎ≥Ў™ўВЎ±ЎІЎ± ЎІўДЎ®ўЖЎ≤ўКўЖ. ЎІўДЎЃўКЎІЎ±ЎІЎ™ ЎІўДЎ£ЎЃЎ±ўЙ ЎЇўКЎ± ЎµЎ≠ўКЎ≠Ў© (ўДЎІ ўКўИЎђЎѓ Ў∞Ў±Ў© ўЕЎ±ўГЎ≤ўКЎ©ЎМ ўИЎІўДЎ±ўИЎІЎ®ЎЈ ўДўКЎ≥Ў™ ўЕЎ™Ў®ЎІЎѓўДЎ© Ў®ЎіўГўД ЎЂЎІЎ®Ў™ Ў£Ў≠ЎІЎѓўК/ЎЂўЖЎІЎ¶ўК).",
      "test_type": "adaptive",
      "difficulty": "hard",
      "topic_ar": "ЎІўДўГўКўЕўКЎІЎ° ЎІўДЎђЎ≤ўКЎ¶ўКЎ©",
      "matching_pairs_en": [],
      "question_ar": "Ў£ўК ЎІўДЎђўЕўД ЎІўДЎ™ЎІўДўКЎ© ЎµЎ≠ўКЎ≠Ў© Ў®ЎІўДўЖЎ≥Ў®Ў© ўДўДўЗўОўКўГўОўД ЎІўДЎ®ўЖЎ≤ўКўЖ (C6H6)ЎЯ",
      "explanation_en": "Benzene has ѕА-electron delocalization (resonance) that makes all CвАУC bonds equal with an intermediate length between single and double bonds, explaining its stability. Other options are incorrect (no central atom; bonds are not fixed alternating single/double).",
      "classify_categories_ar": [],
      "classify_items_en": [],
      "grade": 11,
      "matching_pairs_ar": [],
      "question_en": "Which of the following statements is true about benzene (C6H6)?",
      "classify_categories_en": [],
      "classify_items_ar": [],
      "options_ar": [
        "ўДўЗ Ў≥Ў™Ў© Ў±ўИЎІЎ®ЎЈ ўЕўБЎ±ЎѓЎ© Ў®ўКўЖ ўГЎ±Ў®ўИўЖ ўИўГЎ±Ў®ўИўЖ ўБўВЎЈ",
        "Ў±ўИЎІЎ®ЎЈ CвАУC ўБўКўЗ Ў™Ў™ўЖЎІўИЎ® Ў™ўЕЎІўЕўЛЎІ Ў®ўКўЖ Ў£Ў≠ЎІЎѓўК ўИЎЂўЖЎІЎ¶ўК",
        "ЎђўЕўКЎє Ў±ўИЎІЎ®ЎЈ CвАУC ўЕЎ™Ў≥ЎІўИўКЎ© ўИЎЈўИўДўЗЎІ ўЕЎ™ўИЎ≥ЎЈ ўЖЎ™ўКЎђЎ© ўДўДЎ™ЎіЎІЎ±ўГ ЎІўДЎ•ўДўГЎ™Ў±ўИўЖўК (delocalization)",
        "ЎІўДЎ∞Ў±Ў© ЎІўДўЕЎ±ўГЎ≤ўКЎ© sp hybridized"
      ],
      "id": "6a4a009c91ae4df21ea3969c",
      "created_date": "2026-07-05T06:58:36.341000",
      "updated_date": "2026-07-05T06:58:36.341000",
      "created_by_id": "service_54c00eed-6486-4029-9a2e-cf5b715d0b73",
      "is_sample": false
    },
    {
      "ordering_items_ar": [],
      "question_type": "multiple_choice",
      "options_en": [
        "1/4",
        "1/2",
        "2/3",
        "3/4"
      ],
      "correct_answer": "2",
      "ordering_items_en": [],
      "topic_en": "Genetics and genes",
      "explanation_ar": "Ў™ўИЎ≤ўКЎє ЎІўДўЖЎ≥ўД ўЕўЖ Tt √Ч Tt ўЗўИ: TT : Tt : tt = 1:2:1. ЎІўДўЖЎ®ЎІЎ™ЎІЎ™ ЎІўДЎЈўИўКўДЎ© ўЗўК TT ўИ Tt (3 Ў≠ЎІўДЎІЎ™). ўЕўЖ Ў®ўКўЖўЗЎІ Tt ўКўЕЎЂўД 2 ўЕўЖ 3 вЗТ ЎІўДЎІЎ≠Ў™ўЕЎІўД 2/3.",
      "test_type": "adaptive",
      "difficulty": "hard",
      "topic_ar": "ЎІўДўИЎ±ЎІЎЂЎ© ўИЎІўДЎђўКўЖЎІЎ™",
      "matching_pairs_en": [],
      "question_ar": "ўБўК ўЖЎ®ЎІЎ™ ЎІўДЎ®ЎІЎ≤ўДЎІЎ°ЎМ ЎІўДЎµўБЎ© ЎІўДЎЈўИЎІўД (T) Ў≥ЎІЎ¶ЎѓЎ© ЎєўДўЙ ЎІўДўВўРЎµўОЎ± (t). Ў™ўЕ Ў™Ў≤ЎІўИЎђ ўЖЎ®ЎІЎ™ўКўЖ ўЕЎ™ўЕЎІЎЂўДўКўЖ ЎІўДўДЎІўВЎ≠Ў© (heterozygous). ўЕЎІ ЎІЎ≠Ў™ўЕЎІўД Ў£ўЖ ўКўГўИўЖ ўЖЎ®ЎІЎ™ ЎЈўИўКўД ЎІўДЎЄЎІўЗЎ± ўДўГўЖ ўЕЎ™ўЕЎІЎЂўД ЎІўДўДЎІўВЎ≠Ў© (Ў£ўК ўИўОЎ±ўЙ ЎІўДЎђўКўЖ)ЎЯ",
      "explanation_en": "For Tt √Ч Tt the genotypic ratio is TT:Tt:tt = 1:2:1. Tall phenotypes are TT and Tt (3 instances); among tall plants, heterozygotes are 2 of 3 вЗТ probability = 2/3.",
      "classify_categories_ar": [],
      "classify_items_en": [],
      "grade": 11,
      "matching_pairs_ar": [],
      "question_en": "In pea plants tall (T) is dominant to short (t). Two heterozygotes are crossed. What is the probability that a tall phenotype plant is heterozygous (i.e., a carrier)?",
      "classify_categories_en": [],
      "classify_items_ar": [],
      "options_ar": [
        "1/4",
        "1/2",
        "2/3",
        "3/4"
      ],
      "id": "6a4a009c91ae4df21ea3969d",
      "created_date": "2026-07-05T06:58:36.341000",
      "updated_date": "2026-07-05T06:58:36.341000",
      "created_by_id": "service_54c00eed-6486-4029-9a2e-cf5b715d0b73",
      "is_sample": false
    },
    {
      "ordering_items_ar": [],
      "question_type": "multiple_choice",
      "options_en": [
        "Traditional schooling is sufficient for life",
        "Lifelong learning is necessary to keep up with changes",
        "Specialization is harmful to modern careers",
        "Technology prevents learning"
      ],
      "correct_answer": "1",
      "ordering_items_en": [],
      "topic_en": "Critical comprehension",
      "explanation_ar": "ЎІўДўБўВЎ±Ў© Ў™Ў§ўГЎѓ Ў£ўЖ ЎІўДЎ™ЎєўДўЕ ўДЎІ ўКўВЎ™ЎµЎ± ЎєўДўЙ ЎІўДЎ™ЎєўДўКўЕ ЎІўДЎІЎ®Ў™ЎѓЎІЎ¶ўК/ЎІўДЎЂЎІўЖўИўК ўИЎ£ўЖ ЎІўДЎ™ЎєўДўЕ ўЕЎѓўЙ ЎІўДЎ≠ўКЎІЎ© Ў£ЎµЎ®Ў≠ ЎґЎ±ўИЎ±ўКўЛЎІ ўДўЕўИЎІўГЎ®Ў© ЎІўДЎ™ЎЈўИЎ±ЎЫ ўЗЎ∞ўЗ ўЗўК ЎІўДўБўГЎ±Ў© ЎІўДЎ±Ў¶ўКЎ≥ўКЎ©.",
      "test_type": "adaptive",
      "difficulty": "hard",
      "topic_ar": "ЎІўДЎІЎ≥Ў™ўКЎєЎІЎ® ЎІўДўЖўВЎѓўК",
      "matching_pairs_en": [],
      "question_ar": "ЎІўВЎ±Ў£ ЎІўДўБўВЎ±Ў© ЎІўДЎ™ЎІўДўКЎ©: \"ўБўК ЎєЎІўДўЕ ўКЎ≤ЎѓЎІЎѓ ўБўКўЗ Ў™Ў®ЎІЎѓўД ЎІўДўЕЎєЎ±ўБЎ© ўИЎ≥Ў±ЎєЎ© ЎІўДЎ™ЎЇўКЎ± ўБўК Ў≥ўИўВ ЎІўДЎєўЕўДЎМ ўДўЕ ўКЎєЎѓ ЎІўДЎ™ЎєўДўЕ ўЕЎ≠ЎµўИЎ±ўЛЎІ ўБўК Ў≥ўЖўИЎІЎ™ ЎІўДЎѓЎ±ЎІЎ≥Ў© ЎІўДЎ£ўИўДўЙ. ЎІўДЎ™ЎєўДўЕ ўЕЎѓўЙ ЎІўДЎ≠ўКЎІЎ© Ў£ЎµЎ®Ў≠ Ў≠ЎІЎђЎ© ўДЎ™Ў≠ЎѓўКЎЂ ЎІўДўЕўЗЎІЎ±ЎІЎ™ ўИўЕўИЎІўГЎ®Ў© ЎІўДЎ™ЎЈўИЎ± ЎІўДЎ™ўГўЖўИўДўИЎђўК ўИЎІўДЎІўВЎ™ЎµЎІЎѓўК.\" ўЕЎІ ЎІўДўБўГЎ±Ў© ЎІўДЎ±Ў¶ўКЎ≥Ў© ўДўДўБўВЎ±Ў©ЎЯ",
      "explanation_en": "The passage emphasizes that learning is not confined to initial schooling and that lifelong learning has become necessary to keep up with developments; this is the main idea.",
      "classify_categories_ar": [],
      "classify_items_en": [],
      "grade": 11,
      "matching_pairs_ar": [],
      "question_en": "Read the passage: \"In a world with increasing knowledge exchange and rapid change in the job market, learning is no longer confined to the early years of education. Lifelong learning has become a necessity to update skills and keep up with technological and economic development.\" What is the main idea?",
      "classify_categories_en": [],
      "classify_items_ar": [],
      "options_ar": [
        "ЎІўДЎ™ЎєўДўКўЕ ЎІўДЎ™ўВўДўКЎѓўК ўБўК ЎІўДўЕЎѓЎІЎ±Ў≥ ўГЎІўБўН ЎЈўИЎІўД ЎІўДЎ≠ўКЎІЎ©",
        "ЎІўДЎ™ЎєўДўЕ ўЕЎѓўЙ ЎІўДЎ≠ўКЎІЎ© ЎґЎ±ўИЎ±Ў© ўДўЕўИЎІўГЎ®Ў© ЎІўДЎ™ЎЇўКЎ±ЎІЎ™",
        "ЎІўДЎ™ЎЃЎµЎµ ЎґЎІЎ± Ў®ЎІўДўЕўЗўЖ ЎІўДЎ≠ЎѓўКЎЂЎ©",
        "ЎІўДЎ™ўГўЖўИўДўИЎђўКЎІ Ў™ўЕўЖЎє ЎІўДЎ™ЎєўДўЕ"
      ],
      "id": "6a4a009c91ae4df21ea3969e",
      "created_date": "2026-07-05T06:58:36.341000",
      "updated_date": "2026-07-05T06:58:36.341000",
      "created_by_id": "service_54c00eed-6486-4029-9a2e-cf5b715d0b73",
      "is_sample": false
    },
    {
      "ordering_items_ar": [],
      "question_type": "multiple_choice",
      "options_en": [
        "¬ђp only",
        "¬ђq only",
        "¬ђp and ¬ђq",
        "Nothing can be deduced"
      ],
      "correct_answer": "2",
      "ordering_items_en": [],
      "topic_en": "Logic and reasoning",
      "explanation_ar": "ўЕўЖ ¬ђr ўИЎ®ЎІўДўЕўВЎІЎ®ўДЎ© ЎІўДўЕўЖЎЈўВўКЎ© ўД (qвЖТr) ўЖЎ≥Ў™ўЖЎ™Ўђ ¬ђq. ЎЂўЕ ўЕўЖ ¬ђq ўИЎ®ЎІўДўЕўВЎІЎ®ўДЎ© ўД (pвЖТq) ўЖЎ≥Ў™ўЖЎ™Ўђ ¬ђp. Ў•Ў∞ўЖ ўГўДЎІ ¬ђp ўИ ¬ђq ўЕЎ≥Ў™ўЖЎ™ЎђЎІўЖ.",
      "test_type": "adaptive",
      "difficulty": "hard",
      "topic_ar": "ЎІўДўЕўЖЎЈўВ ўИЎІўДЎІЎ≥Ў™ЎѓўДЎІўД",
      "matching_pairs_en": [],
      "question_ar": "ўЕЎєЎЈўЙ: (1) Ў•Ў∞ЎІ p ўБЎ•ўЖ q. (2) Ў•Ў∞ЎІ q ўБЎ•ўЖ r. (3) ўДўКЎ≥ r. ўЕЎІ ЎІўДЎ∞ўК ўКўЕўГўЖ ЎІЎ≥Ў™ўЖЎ™ЎІЎђўЗ ўЕўЖЎЈўВўКЎІўЛЎЯ",
      "explanation_en": "From ¬ђr and the contrapositive of (qвЖТr) we get ¬ђq. From ¬ђq and the contrapositive of (pвЖТq) we get ¬ђp. Thus both ¬ђp and ¬ђq are deducible.",
      "classify_categories_ar": [],
      "classify_items_en": [],
      "grade": 11,
      "matching_pairs_ar": [],
      "question_en": "Given: (1) p вЖТ q. (2) q вЖТ r. (3) ¬ђr. What can be logically deduced?",
      "classify_categories_en": [],
      "classify_items_ar": [],
      "options_ar": [
        "¬ђp ўБўВЎЈ",
        "¬ђq ўБўВЎЈ",
        "¬ђp ўИ ¬ђq",
        "ўДЎІ ўКўЕўГўЖ ЎІЎ≥Ў™ўЖЎ™ЎІЎђ ЎіўКЎ°"
      ],
      "id": "6a4a009c91ae4df21ea3969f",
      "created_date": "2026-07-05T06:58:36.341000",
      "updated_date": "2026-07-05T06:58:36.341000",
      "created_by_id": "service_54c00eed-6486-4029-9a2e-cf5b715d0b73",
      "is_sample": false
    },
    {
      "ordering_items_ar": [],
      "question_type": "multiple_choice",
      "options_en": [
        "0",
        "e/2",
        "-e/2",
        "-e"
      ],
      "correct_answer": "2",
      "ordering_items_en": [],
      "topic_en": "Limits and exponential basics",
      "explanation_ar": "ўЖЎ≥Ў™ЎЃЎѓўЕ ln: ln((1+x)^{1/x}) = (1/x)ln(1+x)=1 - x/2 + O(x^2). Ў•Ў∞ўЖ (1+x)^{1/x} = e^{1 - x/2 + ...} = e¬Јe^{-x/2+...} = e(1 - x/2 + ...). ЎІўДўБЎ±ўВ ЎІўДўЕўВЎ≥ўИўЕ ЎєўДўЙ x ўКЎєЎЈўК -e/2.",
      "test_type": "adaptive",
      "difficulty": "hard",
      "topic_ar": "ЎІўДўЖўЗЎІўКЎІЎ™ ўИЎІўДЎ£Ў≥ЎІЎ≥ўКЎІЎ™ ЎІўДЎ£Ў≥ўКЎ©",
      "matching_pairs_en": [],
      "question_ar": "ЎІЎ≠Ў≥Ў®: lim_{xвЖТ0} [ (1+x)^{1/x} - e ] / x",
      "explanation_en": "Use ln: ln((1+x)^{1/x}) = (1/x)ln(1+x)=1 - x/2 + O(x^2). Thus (1+x)^{1/x} = e^{1 - x/2 + ...} = e¬Ј(1 - x/2 + ...). The difference divided by x tends to -e/2.",
      "classify_categories_ar": [],
      "classify_items_en": [],
      "grade": 11,
      "matching_pairs_ar": [],
      "question_en": "Compute: lim_{xвЖТ0} [ (1+x)^{1/x} - e ] / x",
      "classify_categories_en": [],
      "classify_items_ar": [],
      "options_ar": [
        "0",
        "e/2",
        "-e/2",
        "-e"
      ],
      "id": "6a4a009c91ae4df21ea396a0",
      "created_date": "2026-07-05T06:58:36.341000",
      "updated_date": "2026-07-05T06:58:36.341000",
      "created_by_id": "service_54c00eed-6486-4029-9a2e-cf5b715d0b73",
      "is_sample": false
    },
    {
      "ordering_items_ar": [],
      "question_type": "multiple_choice",
      "options_en": [
        "> 0 and equals 1/p",
        "p > 1 and equals 1/(p-1)",
        "p < 1 and equals 1/(1-p)",
        "Converges for all p and equals ln вИЮ"
      ],
      "correct_answer": "1",
      "ordering_items_en": [],
      "topic_en": "Calculus (improper integrals)",
      "explanation_ar": "вИЂ_{1}^{вИЮ} x^{-p} dx = lim_{RвЖТвИЮ} [ x^{-p+1}/(-p+1) ]_{1}^{R}. ўЗЎ∞ЎІ ўКЎ™ўВЎІЎ±Ў® Ў•Ў∞ЎІ ўИўБўВЎЈ Ў•Ў∞ЎІ -p+1 < 0 вЗТ p>1ЎМ ўИЎ™Ў≥ЎІўИўК 1/(p-1).",
      "test_type": "adaptive",
      "difficulty": "hard",
      "topic_ar": "ЎІўДЎ™ўБЎІЎґўД ўИЎІўДЎ™ўГЎІўЕўД (ЎІўДЎ™ўВЎІЎ±Ў® ЎЇўКЎ± ЎІўДўЕЎ≠ЎѓўИЎѓ)",
      "matching_pairs_en": [],
      "question_ar": "Ў®ЎІўДўЖЎ≥Ў®Ў© ўДўДўВўКўЕЎ© p ЎІўДЎ≠ўВўКўВўКЎ©ЎМ ўЕЎ™ўЙ ўКЎ™ўВЎІЎ±Ў® ЎІўДЎ™ўГЎІўЕўД ЎЇўКЎ± ЎІўДўЕЎ≠ЎѓўИЎѓ вИЂ_{1}^{вИЮ} 1/x^{p} dxЎМ ўИЎ•Ў∞ЎІ Ў™ўВЎІЎ±Ўє ўБўЕЎІЎ∞ЎІ Ў™Ў≥ЎІўИўК ўВўКўЕЎ™ўЗЎЯ",
      "explanation_en": "Compute вИЂ_{1}^{вИЮ} x^{-p} dx = lim_{RвЖТвИЮ} [ x^{-p+1}/(-p+1) ]_{1}^{R}. Convergence requires -p+1<0 вЗТ p>1, and the value is 1/(p-1).",
      "classify_categories_ar": [],
      "classify_items_en": [],
      "grade": 11,
      "matching_pairs_ar": [],
      "question_en": "For real p, when does the improper integral вИЂ_{1}^{вИЮ} 1/x^{p} dx converge, and if it converges what is its value?",
      "classify_categories_en": [],
      "classify_items_ar": [],
      "options_ar": [
        "> 0 ўИўЕЎ≥ЎІўИўКЎ© 1/p",
        "p > 1 ўИўЕЎ≥ЎІўИўКЎ© 1/(p-1)",
        "p < 1 ўИўЕЎ≥ЎІўИўКЎ© 1/(1-p)",
        "ўДўГўД p ўКЎ™ўВЎІЎ±Ў® ўИўКЎєЎЈўЙ ln вИЮ"
      ],
      "id": "6a4a009c91ae4df21ea396a1",
      "created_date": "2026-07-05T06:58:36.341000",
      "updated_date": "2026-07-05T06:58:36.341000",
      "created_by_id": "service_54c00eed-6486-4029-9a2e-cf5b715d0b73",
      "is_sample": false
    },
    {
      "ordering_items_ar": [],
      "question_type": "multiple_choice",
      "options_en": [
        "вЙИ 30¬∞",
        "вЙИ 45¬∞",
        "вЙИ 63.6¬∞",
        "вЙИ 90¬∞"
      ],
      "correct_answer": "2",
      "ordering_items_en": [],
      "topic_en": "Vectors",
      "explanation_ar": "a¬Јb = 1¬Ј2 + 2¬Ј(-1) + 2¬Ј2 = 4. |a| = вИЪ(1+4+4)=3ЎМ |b|=вИЪ(4+1+4)=3. Ў•Ў∞ўЖ cosќЄ = 4/(3¬Ј3)=4/9 вЙИ 0.4444 вЗТ ќЄ вЙИ arccos(4/9) вЙИ 63.6¬∞.",
      "test_type": "adaptive",
      "difficulty": "hard",
      "topic_ar": "ЎІўДўЕЎ™ЎђўЗЎІЎ™",
      "matching_pairs_en": [],
      "question_ar": "ЎІЎєЎЈўЙ ЎІўДўЕЎ™ЎђўЗЎІўЖ a = (1,2,2) ўИ b = (2,-1,2). ўЕЎІ ўВўКЎІЎ≥ ЎІўДЎ≤ЎІўИўКЎ© Ў®ўКўЖўЗўЕЎІ Ў™ўВЎ±ўКЎ®ўЛЎІЎЯ",
      "explanation_en": "a¬Јb = 1¬Ј2 + 2¬Ј(-1) + 2¬Ј2 = 4. |a| = вИЪ(1+4+4)=3, |b|=вИЪ(4+1+4)=3. So cosќЄ = 4/(3¬Ј3)=4/9 вЙИ0.4444 вЗТ ќЄ вЙИ arccos(4/9) вЙИ63.6¬∞.",
      "classify_categories_ar": [],
      "classify_items_en": [],
      "grade": 11,
      "matching_pairs_ar": [],
      "question_en": "Given vectors a = (1,2,2) and b = (2,-1,2). What is the angle between them approximately?",
      "classify_categories_en": [],
      "classify_items_ar": [],
      "options_ar": [
        "вЙИ 30¬∞",
        "вЙИ 45¬∞",
        "вЙИ 63.6¬∞",
        "вЙИ 90¬∞"
      ],
      "id": "6a4a009c91ae4df21ea396a2",
      "created_date": "2026-07-05T06:58:36.341000",
      "updated_date": "2026-07-05T06:58:36.341000",
      "created_by_id": "service_54c00eed-6486-4029-9a2e-cf5b715d0b73",
      "is_sample": false
    },
    {
      "ordering_items_ar": [],
      "question_type": "multiple_choice",
      "options_en": [
        "5",
        "6",
        "7",
        "8"
      ],
      "correct_answer": "2",
      "ordering_items_en": [],
      "topic_en": "Functions and limits",
      "explanation_ar": "Ў®ЎІўДЎ™ЎєўИўКЎґ ЎІўДўЕЎ®ЎІЎіЎ±: 3¬Ј2 + 1 = 7.",
      "test_type": "adaptive",
      "difficulty": "easy",
      "topic_ar": "ЎІўДЎѓўИЎІўД ўИЎІўДўЖўЗЎІўКЎІЎ™",
      "matching_pairs_en": [],
      "question_ar": "Ў£ўИЎђЎѓ ЎІўДўЖўЗЎІўКЎ© ЎєўЖЎѓ xвЖТ2 ўДўДЎѓЎІўДЎ© 3x + 1.",
      "explanation_en": "Direct substitution: 3¬Ј2 + 1 = 7.",
      "classify_categories_ar": [],
      "classify_items_en": [],
      "grade": 11,
      "matching_pairs_ar": [],
      "question_en": "Find the limit as xвЖТ2 of the function 3x + 1.",
      "classify_categories_en": [],
      "classify_items_ar": [],
      "options_ar": [
        "5",
        "6",
        "7",
        "8"
      ],
      "id": "6a4a009c91ae4df21ea3967a",
      "created_date": "2026-07-05T06:58:36.340000",
      "updated_date": "2026-07-05T06:58:36.340000",
      "created_by_id": "service_54c00eed-6486-4029-9a2e-cf5b715d0b73",
      "is_sample": false
    },
    {
      "ordering_items_ar": [],
      "question_type": "multiple_choice",
      "options_en": [
        "x > 1",
        "x вЙ• 1",
        "x вЙ§ 1",
        "x < 1"
      ],
      "correct_answer": "1",
      "ordering_items_en": [],
      "topic_en": "Functions and limits",
      "explanation_ar": "ЎѓЎІЎЃўД ЎІўДЎђЎ∞Ў± ўКЎђЎ® Ў£ўЖ ўКўГўИўЖ вЙ• 0ЎМ Ў£ўК x - 1 вЙ• 0 вЗТ x вЙ• 1.",
      "test_type": "adaptive",
      "difficulty": "easy",
      "topic_ar": "ЎІўДЎѓўИЎІўД ўИЎІўДўЖўЗЎІўКЎІЎ™",
      "matching_pairs_en": [],
      "question_ar": "ўЕЎІ ўЗўИ ўЕЎђЎІўД ЎІўДЎѓЎІўДЎ© f(x) = вИЪ(x - 1)ЎЯ",
      "explanation_en": "The radicand must be вЙ• 0, so x - 1 вЙ• 0 вЗТ x вЙ• 1.",
      "classify_categories_ar": [],
      "classify_items_en": [],
      "grade": 11,
      "matching_pairs_ar": [],
      "question_en": "What is the domain of f(x) = вИЪ(x - 1)?",
      "classify_categories_en": [],
      "classify_items_ar": [],
      "options_ar": [
        "x > 1",
        "x вЙ• 1",
        "x вЙ§ 1",
        "x < 1"
      ],
      "id": "6a4a009c91ae4df21ea3967b",
      "created_date": "2026-07-05T06:58:36.340000",
      "updated_date": "2026-07-05T06:58:36.340000",
      "created_by_id": "service_54c00eed-6486-4029-9a2e-cf5b715d0b73",
      "is_sample": false
    },
    {
      "ordering_items_ar": [],
      "question_type": "multiple_choice",
      "options_en": [
        "x",
        "2x",
        "x^2",
        "2"
      ],
      "correct_answer": "1",
      "ordering_items_en": [],
      "topic_en": "Calculus (differentiation/integration)",
      "explanation_ar": "ўВЎІўЖўИўЖ ЎІўДўЕЎіЎ™ўВЎ© ўДўРx^n ўЗўИ n¬Јx^{n-1}ЎМ ўЗўЖЎІ 2¬Јx^{1} = 2x.",
      "test_type": "adaptive",
      "difficulty": "easy",
      "topic_ar": "ЎІўДЎ™ўБЎІЎґўД ўИЎІўДЎ™ўГЎІўЕўД",
      "matching_pairs_en": [],
      "question_ar": "ўЕЎІ ўЕЎіЎ™ўВЎ© ЎІўДЎѓЎІўДЎ© f(x) = x^2ЎЯ",
      "explanation_en": "Using d/dx x^n = n¬Јx^{n-1}, here 2¬Јx^{1} = 2x.",
      "classify_categories_ar": [],
      "classify_items_en": [],
      "grade": 11,
      "matching_pairs_ar": [],
      "question_en": "What is the derivative of f(x) = x^2?",
      "classify_categories_en": [],
      "classify_items_ar": [],
      "options_ar": [
        "x",
        "2x",
        "x^2",
        "2"
      ],
      "id": "6a4a009c91ae4df21ea3967c",
      "created_date": "2026-07-05T06:58:36.340000",
      "updated_date": "2026-07-05T06:58:36.340000",
      "created_by_id": "service_54c00eed-6486-4029-9a2e-cf5b715d0b73",
      "is_sample": false
    },
    {
      "ordering_items_ar": [],
      "question_type": "multiple_choice",
      "options_en": [
        "x^2 + C",
        "2x + C",
        "x + C",
        "x^2/2 + C"
      ],
      "correct_answer": "0",
      "ordering_items_en": [],
      "topic_en": "Calculus (differentiation/integration)",
      "explanation_ar": "вИЂ2x dx = 2¬Ј(x^2/2) + C = x^2 + C.",
      "test_type": "adaptive",
      "difficulty": "easy",
      "topic_ar": "ЎІўДЎ™ўБЎІЎґўД ўИЎІўДЎ™ўГЎІўЕўД",
      "matching_pairs_en": [],
      "question_ar": "ўЕЎІ ўВўКўЕЎ© ЎІўДЎ™ўГЎІўЕўД вИЂ 2x dx ЎЯ",
      "explanation_en": "вИЂ2x dx = 2¬Ј(x^2/2) + C = x^2 + C.",
      "classify_categories_ar": [],
      "classify_items_en": [],
      "grade": 11,
      "matching_pairs_ar": [],
      "question_en": "What is the value of the integral вИЂ 2x dx ?",
      "classify_categories_en": [],
      "classify_items_ar": [],
      "options_ar": [
        "x^2 + C",
        "2x + C",
        "x + C",
        "x^2/2 + C"
      ],
      "id": "6a4a009c91ae4df21ea3967d",
      "created_date": "2026-07-05T06:58:36.340000",
      "updated_date": "2026-07-05T06:58:36.340000",
      "created_by_id": "service_54c00eed-6486-4029-9a2e-cf5b715d0b73",
      "is_sample": false
    },
    {
      "ordering_items_ar": [],
      "question_type": "multiple_choice",
      "options_en": [
        "x = 1 or 6",
        "x = 2 or 3",
        "x = -2 or -3",
        "x = -1 or -6"
      ],
      "correct_answer": "1",
      "ordering_items_en": [],
      "topic_en": "Advanced algebra",
      "explanation_ar": "Ў™ўБўГўКўГ: x^2 - 5x + 6 = (x - 2)(x - 3)ЎМ Ў•Ў∞ўЖ ЎІўДЎђЎ∞ўИЎ± 2 ўИ3.",
      "test_type": "adaptive",
      "difficulty": "easy",
      "topic_ar": "ЎІўДЎђЎ®Ў± ЎІўДўЕЎ™ўВЎѓўЕ",
      "matching_pairs_en": [],
      "question_ar": "Ў≠ўД ЎІўДўЕЎєЎІЎѓўДЎ© x^2 - 5x + 6 = 0.",
      "explanation_en": "Factor: x^2 - 5x + 6 = (x - 2)(x - 3), so roots are 2 and 3.",
      "classify_categories_ar": [],
      "classify_items_en": [],
      "grade": 11,
      "matching_pairs_ar": [],
      "question_en": "Solve the equation x^2 - 5x + 6 = 0.",
      "classify_categories_en": [],
      "classify_items_ar": [],
      "options_ar": [
        "x = 1 Ў£ўИ 6",
        "x = 2 Ў£ўИ 3",
        "x = -2 Ў£ўИ -3",
        "x = -1 Ў£ўИ -6"
      ],
      "id": "6a4a009c91ae4df21ea3967e",
      "created_date": "2026-07-05T06:58:36.340000",
      "updated_date": "2026-07-05T06:58:36.340000",
      "created_by_id": "service_54c00eed-6486-4029-9a2e-cf5b715d0b73",
      "is_sample": false
    },
    {
      "ordering_items_ar": [],
      "question_type": "multiple_choice",
      "options_en": [
        "(x + 1)/2",
        "(x - 1)/2",
        "2x - 1",
        "1/(2x + 1)"
      ],
      "correct_answer": "1",
      "ordering_items_en": [],
      "topic_en": "Advanced algebra",
      "explanation_ar": "ўДЎ™ЎєўКўКўЖ ЎІўДЎєўГЎ≥: y = 2x + 1 вЗТ x = (y - 1)/2ЎМ ўЖўГЎ™Ў® f^{-1}(x) = (x - 1)/2.",
      "test_type": "adaptive",
      "difficulty": "easy",
      "topic_ar": "ЎІўДЎђЎ®Ў± ЎІўДўЕЎ™ўВЎѓўЕ",
      "matching_pairs_en": [],
      "question_ar": "ўЕЎІ ЎІўДЎѓЎІўДЎ© ЎІўДЎєўГЎ≥ўКЎ© ўДўА f(x) = 2x + 1 ЎЯ",
      "explanation_en": "Set y = 2x + 1 вЗТ x = (y - 1)/2, so f^{-1}(x) = (x - 1)/2.",
      "classify_categories_ar": [],
      "classify_items_en": [],
      "grade": 11,
      "matching_pairs_ar": [],
      "question_en": "What is the inverse function of f(x) = 2x + 1 ?",
      "classify_categories_en": [],
      "classify_items_ar": [],
      "options_ar": [
        "(x + 1)/2",
        "(x - 1)/2",
        "2x - 1",
        "1/(2x + 1)"
      ],
      "id": "6a4a009c91ae4df21ea3967f",
      "created_date": "2026-07-05T06:58:36.340000",
      "updated_date": "2026-07-05T06:58:36.340000",
      "created_by_id": "service_54c00eed-6486-4029-9a2e-cf5b715d0b73",
      "is_sample": false
    },
    {
      "ordering_items_ar": [],
      "question_type": "multiple_choice",
      "options_en": [
        "5",
        "7",
        "1",
        "25"
      ],
      "correct_answer": "0",
      "ordering_items_en": [],
      "topic_en": "Vectors and projectile motion",
      "explanation_ar": "ЎІўДўЕўВЎѓЎІЎ± = вИЪ(3^2 + 4^2) = вИЪ(9+16) = вИЪ25 = 5.",
      "test_type": "adaptive",
      "difficulty": "easy",
      "topic_ar": "ЎІўДўЕЎ™ЎђўЗЎІЎ™ ўИЎІўДўЕўВЎ∞ўИўБЎІЎ™",
      "matching_pairs_en": [],
      "question_ar": "ўЕЎІ ўЕўВЎѓЎІЎ± ЎІўДўЕЎ™ЎђўЗ v = (3, 4)ЎЯ",
      "explanation_en": "Magnitude = вИЪ(3^2 + 4^2) = вИЪ25 = 5.",
      "classify_categories_ar": [],
      "classify_items_en": [],
      "grade": 11,
      "matching_pairs_ar": [],
      "question_en": "What is the magnitude of the vector v = (3, 4)?",
      "classify_categories_en": [],
      "classify_items_ar": [],
      "options_ar": [
        "5",
        "7",
        "1",
        "25"
      ],
      "id": "6a4a009c91ae4df21ea39680",
      "created_date": "2026-07-05T06:58:36.340000",
      "updated_date": "2026-07-05T06:58:36.340000",
      "created_by_id": "service_54c00eed-6486-4029-9a2e-cf5b715d0b73",
      "is_sample": false
    },
    {
      "ordering_items_ar": [],
      "question_type": "multiple_choice",
      "options_en": [
        "10 m",
        "20 m",
        "40 m",
        "400 m"
      ],
      "correct_answer": "1",
      "ordering_items_en": [],
      "topic_en": "Vectors and projectile motion",
      "explanation_ar": "ЎІўДЎІЎ±Ў™ўБЎІЎє ЎІўДЎ£ўВЎµўЙ = v0^2/(2g) = 20^2/(2¬Ј10) = 400/20 = 20 ўЕ.",
      "test_type": "adaptive",
      "difficulty": "easy",
      "topic_ar": "ЎІўДўЕЎ™ЎђўЗЎІЎ™ ўИЎІўДўЕўВЎ∞ўИўБЎІЎ™",
      "matching_pairs_en": [],
      "question_ar": "ўВЎ∞ўКўБЎ© Ў£ЎЈўДўВЎ™ Ў±Ў£Ў≥ўКЎІўЛ Ў®Ў≥Ў±ЎєЎ© 20 ўЕ/ЎЂ. (ЎЃ=10 ўЕ/ЎЂ^2). ўЕЎІ Ў£ўВЎµўЙ ЎІЎ±Ў™ўБЎІЎє Ў™ЎµўД Ў•ўДўКўЗЎЯ",
      "explanation_en": "Max height = v0^2/(2g) = 20^2/(2¬Ј10) = 400/20 = 20 m.",
      "classify_categories_ar": [],
      "classify_items_en": [],
      "grade": 11,
      "matching_pairs_ar": [],
      "question_en": "A projectile is launched vertically at 20 m/s (g = 10 m/s^2). What maximum height does it reach?",
      "classify_categories_en": [],
      "classify_items_ar": [],
      "options_ar": [
        "10 ўЕ",
        "20 ўЕ",
        "40 ўЕ",
        "400 ўЕ"
      ],
      "id": "6a4a009c91ae4df21ea39681",
      "created_date": "2026-07-05T06:58:36.340000",
      "updated_date": "2026-07-05T06:58:36.340000",
      "created_by_id": "service_54c00eed-6486-4029-9a2e-cf5b715d0b73",
      "is_sample": false
    },
    {
      "ordering_items_ar": [],
      "question_type": "multiple_choice",
      "options_en": [
        "Linear",
        "Tetrahedral",
        "Trigonal planar",
        "Bent (angular)"
      ],
      "correct_answer": "3",
      "ordering_items_en": [],
      "topic_en": "Molecular chemistry",
      "explanation_ar": "ўДўДўЕЎІЎ° Ў≤ЎІўИўКЎ© Ў±Ў®ЎЈ вЙИ 104.5¬∞ ўБЎІўДЎіўГўД ўЕўЖЎ≠ўЖўК (Ў≤ЎІўИўК) Ў®Ў≥Ў®Ў® ўИЎђўИЎѓ Ў≤ўИЎђўКўЖ ЎЇўКЎ± Ў±ЎІЎ®ЎЈўКўЖ ЎєўДўЙ ЎІўДЎ£ўГЎ≥ЎђўКўЖ.",
      "test_type": "adaptive",
      "difficulty": "easy",
      "topic_ar": "ЎІўДўГўКўЕўКЎІЎ° ЎІўДЎђЎ≤ўКЎ¶ўКЎ©",
      "matching_pairs_en": [],
      "question_ar": "ўЕЎІ ЎіўГўД ЎђЎ≤ўКЎ° ЎІўДўЕЎІЎ° H2OЎЯ",
      "explanation_en": "Water has a bond angle вЙИ 104.5¬∞, so it is bent due to two lone pairs on oxygen.",
      "classify_categories_ar": [],
      "classify_items_en": [],
      "grade": 11,
      "matching_pairs_ar": [],
      "question_en": "What is the shape of the H2O (water) molecule?",
      "classify_categories_en": [],
      "classify_items_ar": [],
      "options_ar": [
        "ЎЃЎЈўК",
        "Ў±Ў®ЎІЎєўК ЎІўДЎ≥ЎЈўИЎ≠",
        "ўЕЎ≥ЎЈЎ≠ ўЕЎЂўДЎЂўК",
        "ўЕўЖЎ≠ўЖўК (Ў≤ЎІўИўК)"
      ],
      "id": "6a4a009c91ae4df21ea39682",
      "created_date": "2026-07-05T06:58:36.340000",
      "updated_date": "2026-07-05T06:58:36.340000",
      "created_by_id": "service_54c00eed-6486-4029-9a2e-cf5b715d0b73",
      "is_sample": false
    },
    {
      "ordering_items_ar": [],
      "question_type": "multiple_choice",
      "options_en": [
        "Covalent",
        "Ionic",
        "Metallic",
        "Hydrogen"
      ],
      "correct_answer": "1",
      "ordering_items_en": [],
      "topic_en": "Molecular chemistry",
      "explanation_ar": "NaCl ўКЎ™ўГўИўЖ ўЕўЖ ўБўВЎѓЎІўЖ ЎІўДЎµўИЎѓўКўИўЕ ЎІўДўГЎ™Ў±ўИўЖЎІўЛ ўИўГЎ≥Ў® ЎІўДўГўДўИЎ± ўДўЗЎМ ўЕўЕЎІ ўКЎіўГўД Ў±ўИЎІЎ®ЎЈ Ў£ўКўИўЖўКЎ© Ў®ўКўЖ ЎІўДЎ£ўКўИўЖЎІЎ™.",
      "test_type": "adaptive",
      "difficulty": "easy",
      "topic_ar": "ЎІўДўГўКўЕўКЎІЎ° ЎІўДЎђЎ≤ўКЎ¶ўКЎ©",
      "matching_pairs_en": [],
      "question_ar": "ўЕЎІ ўЖўИЎє ЎІўДЎ±ЎІЎ®ЎЈЎ© ўБўК ўЕЎ±ўГЎ® NaClЎЯ",
      "explanation_en": "NaCl forms by Na losing an electron and Cl gaining it, producing ionic bonds between ions.",
      "classify_categories_ar": [],
      "classify_items_en": [],
      "grade": 11,
      "matching_pairs_ar": [],
      "question_en": "What type of bond is present in NaCl?",
      "classify_categories_en": [],
      "classify_items_ar": [],
      "options_ar": [
        "Ў™Ў≥ЎІўЗўЕўКЎ©",
        "Ў£ўКўИўЖўКЎ©",
        "ўБўДЎ≤ўКЎ©",
        "ўЗўКЎѓЎ±ўИЎђўКўЖўКЎ©"
      ],
      "id": "6a4a009c91ae4df21ea39683",
      "created_date": "2026-07-05T06:58:36.340000",
      "updated_date": "2026-07-05T06:58:36.340000",
      "created_by_id": "service_54c00eed-6486-4029-9a2e-cf5b715d0b73",
      "is_sample": false
    },
    {
      "ordering_items_ar": [],
      "question_type": "multiple_choice",
      "options_en": [
        "50%",
        "25%",
        "75%",
        "0%"
      ],
      "correct_answer": "1",
      "ordering_items_en": [],
      "topic_en": "Genetics and genes",
      "explanation_ar": "ўЕЎ±Ў®Ўє Ў®ўИўЖўРЎ™ ўКЎєЎЈўК ЎІўДўЖЎ≥Ў®: AA, Aa, Aa, aa вЖТ ЎІЎ≠Ў™ўЕЎІўД aa = 1 ўЕўЖ 4 = 25%.",
      "test_type": "adaptive",
      "difficulty": "easy",
      "topic_ar": "ЎІўДўИЎ±ЎІЎЂЎ© ўИЎІўДЎђўКўЖЎІЎ™",
      "matching_pairs_en": [],
      "question_ar": "Ў•Ў∞ЎІ Ў™Ў≤ЎІўИЎђ ўБЎ±ЎѓЎІўЖ ўЕЎ™ЎЇЎІўКЎ±ЎІ ўДўДЎµўБЎ© ЎІўДЎ≥ЎІЎ¶ЎѓЎ© (Aa √Ч Aa)ЎМ ўЕЎІ ЎІЎ≠Ў™ўЕЎІўД Ў£ўЖ ўКўГўИўЖ ЎІўДўЖЎ≥ўД ўЕЎ™ўЖЎ≠ўКЎІўЛ (aa)ЎЯ",
      "explanation_en": "Punnett square yields AA, Aa, Aa, aa вЖТ aa occurs 1 out of 4 = 25%.",
      "classify_categories_ar": [],
      "classify_items_en": [],
      "grade": 11,
      "matching_pairs_ar": [],
      "question_en": "If two heterozygous individuals for a dominant trait mate (Aa √Ч Aa), what is the probability the offspring is recessive (aa)?",
      "classify_categories_en": [],
      "classify_items_ar": [],
      "options_ar": [
        "50%",
        "25%",
        "75%",
        "0%"
      ],
      "id": "6a4a009c91ae4df21ea39684",
      "created_date": "2026-07-05T06:58:36.340000",
      "updated_date": "2026-07-05T06:58:36.340000",
      "created_by_id": "service_54c00eed-6486-4029-9a2e-cf5b715d0b73",
      "is_sample": false
    },
    {
      "ordering_items_ar": [],
      "question_type": "multiple_choice",
      "options_en": [
        "Reading is a waste of time",
        "Reading is useful to broaden horizons and improve thinking",
        "Books are expensive",
        "Reading weakens memory"
      ],
      "correct_answer": "1",
      "ordering_items_en": [],
      "topic_en": "Critical reading/comprehension",
      "explanation_ar": "ЎІўДўЖЎµ ўКЎ∞ўГЎ± ўБўИЎІЎ¶Ўѓ ЎІўДўВЎ±ЎІЎ°Ў© ўИЎІЎЂЎ±ўЗЎІ ЎєўДўЙ ЎІўДЎ™ўБўГўКЎ± ўИЎІўДўЕЎєЎ±ўБЎ©ЎМ ўДЎ∞ЎІ ЎІўДўБўГЎ±Ў© ЎІўДЎ£Ў≥ЎІЎ≥ўКЎ© ўЗўК ўБЎІЎ¶ЎѓЎ™ўЗЎІ ўДЎ™ўИЎ≥ўКЎє ЎІўДўЕЎѓЎІЎ±ўГ ўИЎ™Ў≠Ў≥ўКўЖ ЎІўДЎ™ўБўГўКЎ±.",
      "test_type": "adaptive",
      "difficulty": "easy",
      "topic_ar": "ЎІўДЎІЎ≥Ў™ўКЎєЎІЎ® ЎІўДўЖўВЎѓўК",
      "matching_pairs_en": [],
      "question_ar": "ЎІўВЎ±Ў£ ЎІўДўЖЎµ ЎІўДўВЎµўКЎ±: \"ЎІўДўВЎ±ЎІЎ°Ў© Ў™ўИЎ≥Ўє ЎІўДўЕЎѓЎІЎ±ўГ ўИЎ™ўПЎєЎ≤ўСЎ≤ ЎІўДўВЎѓЎ±Ў© ЎєўДўЙ ЎІўДЎ™ўБўГўКЎ± ўИЎІўДЎ™Ў≠ўДўКўДЎМ ўГўЕЎІ Ў™Ў≤ўИЎѓўЖЎІ Ў®ўЕЎµЎІЎѓЎ± ўЕЎєЎ±ўБЎ© ўЕЎ™ўЖўИЎєЎ©.\" ўЕЎІ ЎІўДўБўГЎ±Ў© ЎІўДЎ±Ў¶ўКЎ≥Ў© ўДўДўЖЎµЎЯ",
      "explanation_en": "The text describes benefits of reading on thinking and knowledge, so the main idea is that reading broadens horizons and improves thinking.",
      "classify_categories_ar": [],
      "classify_items_en": [],
      "grade": 11,
      "matching_pairs_ar": [],
      "question_en": "Read the short text: \"Reading broadens horizons and enhances thinking and analysis, and provides us with diverse sources of knowledge.\" What is the main idea of the text?",
      "classify_categories_en": [],
      "classify_items_ar": [],
      "options_ar": [
        "ЎІўДўВЎ±ЎІЎ°Ў© ўЕЎґўКЎєЎ© ўДўДўИўВЎ™",
        "ЎІўДўВЎ±ЎІЎ°Ў© ўЕўБўКЎѓЎ© ўДЎ™ўИЎ≥ўКЎє ЎІўДўЕЎѓЎІЎ±ўГ ўИЎ™Ў≠Ў≥ўКўЖ ЎІўДЎ™ўБўГўКЎ±",
        "ЎІўДўГЎ™Ў® ЎЇЎІўДўКЎ© ЎІўДЎЂўЕўЖ",
        "ЎІўДўВЎ±ЎІЎ°Ў© Ў™ўПЎґЎєўБ ЎІўДЎ∞ЎІўГЎ±Ў©"
      ],
      "id": "6a4a009c91ae4df21ea39685",
      "created_date": "2026-07-05T06:58:36.340000",
      "updated_date": "2026-07-05T06:58:36.340000",
      "created_by_id": "service_54c00eed-6486-4029-9a2e-cf5b715d0b73",
      "is_sample": false
    },
    {
      "ordering_items_ar": [],
      "question_type": "multiple_choice",
      "options_en": [
        "Yes, always",
        "No, not necessarily",
        "Yes, if A equals B",
        "Cannot determine"
      ],
      "correct_answer": "1",
      "ordering_items_en": [],
      "topic_en": "Logic and reasoning",
      "explanation_ar": "ўЗЎ∞ЎІ ЎЇўКЎ± ўЕЎґўЕўИўЖЎЫ ўВЎѓ Ў™ўГўИўЖ ЎєўЖЎІЎµЎ± A ўГўДўЗЎІ ЎґўЕўЖ ЎђЎ≤Ў° ўЕўЖ B ЎІўДЎ∞ўК ўДЎІ ўКЎ™ўВЎІЎЈЎє ўЕЎє Ў∞ўДўГ ЎІўДЎђЎ≤Ў° ўЕўЖ B ЎІўДЎ∞ўК ўЗўИ C. ўЕЎЂЎІўД: A = {1}ЎМ B = {1,2}ЎМ C = {2}.",
      "test_type": "adaptive",
      "difficulty": "easy",
      "topic_ar": "ЎІўДўЕўЖЎЈўВ ўИЎІўДЎІЎ≥Ў™ЎѓўДЎІўД",
      "matching_pairs_en": [],
      "question_ar": "Ў•Ў∞ЎІ ўГўД A ўЗўК B ўИЎ®ЎєЎґ B ўЗўК CЎМ ўЗўД ўЖЎ≥Ў™ЎЈўКЎє ЎІўДЎІЎ≥Ў™ўЖЎ™ЎІЎђ Ў£ўЖ Ў®ЎєЎґ A ўЗўК CЎЯ",
      "explanation_en": "Not guaranteed; A could lie in a portion of B that does not overlap with the part of B that is C. Example: A={1}, B={1,2}, C={2}.",
      "classify_categories_ar": [],
      "classify_items_en": [],
      "grade": 11,
      "matching_pairs_ar": [],
      "question_en": "If all A are B and some B are C, can we conclude that some A are C?",
      "classify_categories_en": [],
      "classify_items_ar": [],
      "options_ar": [
        "ўЖЎєўЕ ЎѓЎІЎ¶ўЕЎІ",
        "ўДЎІ ўДўКЎ≥ Ў®ЎІўДЎґЎ±ўИЎ±Ў©",
        "ўЖЎєўЕ Ў•Ў∞ЎІ ўГЎІўЖ A ўКЎ≥ЎІўИўК B",
        "ўДЎІ ўКўЕўГўЖ Ў™Ў≠ЎѓўКЎѓ"
      ],
      "id": "6a4a009c91ae4df21ea39686",
      "created_date": "2026-07-05T06:58:36.340000",
      "updated_date": "2026-07-05T06:58:36.340000",
      "created_by_id": "service_54c00eed-6486-4029-9a2e-cf5b715d0b73",
      "is_sample": false
    },
    {
      "ordering_items_ar": [],
      "question_type": "multiple_choice",
      "options_en": [
        "p is true",
        "p is false",
        "p may be true or false",
        "Cannot determine"
      ],
      "correct_answer": "1",
      "ordering_items_en": [],
      "topic_en": "Logic and reasoning",
      "explanation_ar": "ўЕўЖЎЈўВўКЎІўЛЎМ Ў•Ў∞ЎІ p вЖТ q ўИ q ЎЃЎІЎЈЎ¶Ў©ЎМ ўБЎ•ўЖўЖЎІ ўЖЎ≥Ў™ўЖЎ™Ўђ ¬ђq вЗТ ¬ђp (ЎІўДЎІЎ≥Ў™ЎѓўДЎІўД Ў®ЎІўДЎ™Ў®ЎІўКўЖ)ЎМ Ў£ўК p ЎЇўКЎ± ЎµЎ≠ўКЎ≠Ў©.",
      "test_type": "adaptive",
      "difficulty": "easy",
      "topic_ar": "ЎІўДўЕўЖЎЈўВ ўИЎІўДЎІЎ≥Ў™ЎѓўДЎІўД",
      "matching_pairs_en": [],
      "question_ar": "Ў•Ў∞ЎІ ўГЎІўЖ ЎІўДЎ≠ўГўЕ ЎІўДЎіЎ±ЎЈўК p вЖТ q ЎµЎ≠ўКЎ≠ўЛЎІ ўИўЕЎєЎ±ўИўБўЛЎІ Ў£ўЖ q ЎЇўКЎ± ЎµЎ≠ўКЎ≠Ў©ЎМ ўЕЎІЎ∞ЎІ ўЖЎ≥Ў™ўЖЎ™Ўђ ЎєўЖ pЎЯ",
      "explanation_en": "Logically, from p вЖТ q and q false, we get ¬ђq вЗТ ¬ђp (contrapositive), so p must be false.",
      "classify_categories_ar": [],
      "classify_items_en": [],
      "grade": 11,
      "matching_pairs_ar": [],
      "question_en": "If the conditional statement p вЖТ q is true and q is known to be false, what can we conclude about p?",
      "classify_categories_en": [],
      "classify_items_ar": [],
      "options_ar": [
        "p ЎµЎ≠ўКЎ≠Ў©",
        "p ЎЇўКЎ± ЎµЎ≠ўКЎ≠Ў©",
        "p ўВЎѓ Ў™ўГўИўЖ ЎµЎ≠ўКЎ≠Ў© Ў£ўИ ЎЃЎІЎЈЎ¶Ў©",
        "ўДЎІ ўКўЕўГўЖ Ў™Ў≠ЎѓўКЎѓ"
      ],
      "id": "6a4a009c91ae4df21ea39687",
      "created_date": "2026-07-05T06:58:36.340000",
      "updated_date": "2026-07-05T06:58:36.340000",
      "created_by_id": "service_54c00eed-6486-4029-9a2e-cf5b715d0b73",
      "is_sample": false
    },
    {
      "ordering_items_ar": [],
      "question_type": "multiple_choice",
      "options_en": [
        "0",
        "2",
        "4",
        "Infinity"
      ],
      "correct_answer": "2",
      "ordering_items_en": [],
      "topic_en": "Functions and Limits",
      "explanation_ar": "Ў®ЎІўДЎ™ЎєўИўКЎґ ЎІўДўЕЎ®ЎІЎіЎ± ўЖЎ≠ЎµўД ЎєўДўЙ ЎіўГўД 0/0ЎМ ўЖЎ®Ў≥ЎЈ ЎІўДўГЎ≥Ў±: (x^2-4)=(x-2)(x+2)ЎЫ ўБЎ™ўГўИўЖ ЎІўДўЖўЗЎІўКЎ© = lim_{xвЖТ2} (x+2)=4.",
      "test_type": "adaptive",
      "difficulty": "medium",
      "topic_ar": "ЎІўДЎѓўИЎІўД ўИЎІўДўЖўЗЎІўКЎІЎ™",
      "matching_pairs_en": [],
      "question_ar": "Ў£ўИЎђЎѓ ўВўКўЕЎ© ЎІўДўЖўЗЎІўКЎ©: lim_{xвЖТ2} (x^2 - 4)/(x - 2).",
      "explanation_en": "Direct substitution gives 0/0. Factor numerator: x^2-4=(x-2)(x+2). Cancel (x-2) and evaluate xвЖТ2: limit = x+2 = 4.",
      "classify_categories_ar": [],
      "classify_items_en": [],
      "grade": 11,
      "matching_pairs_ar": [],
      "question_en": "Find the limit: lim_{xвЖТ2} (x^2 - 4)/(x - 2).",
      "classify_categories_en": [],
      "classify_items_ar": [],
      "options_ar": [
        "0",
        "2",
        "4",
        "ўДЎІ ўЖўЗЎІўКЎ©"
      ],
      "id": "6a4a009c91ae4df21ea39688",
      "created_date": "2026-07-05T06:58:36.340000",
      "updated_date": "2026-07-05T06:58:36.340000",
      "created_by_id": "service_54c00eed-6486-4029-9a2e-cf5b715d0b73",
      "is_sample": false
    },
    {
      "ordering_items_ar": [],
      "question_type": "multiple_choice",
      "options_en": [
        "0",
        "1",
        "2",
        "-1"
      ],
      "correct_answer": "2",
      "ordering_items_en": [],
      "topic_en": "Functions and Limits",
      "explanation_ar": "ўЖЎ®Ў≥ўСЎЈ: (x^2-1)=(x-1)(x+1)ЎМ ўДЎ∞ЎІ Ў≠Ўѓ ЎІўДЎѓЎІўДЎ© ЎєўЖЎѓ xвЖТ1 ўКЎ≥ЎІўИўК 1+1=2. ўКЎђЎ® Ў£ўЖ ўКўГўИўЖ k=2 ўДўДЎІЎ≥Ў™ўЕЎ±ЎІЎ±ўКЎ©.",
      "test_type": "adaptive",
      "difficulty": "medium",
      "topic_ar": "ЎІўДЎѓўИЎІўД ўИЎІўДўЖўЗЎІўКЎІЎ™",
      "matching_pairs_en": [],
      "question_ar": "ўДЎѓЎІўДЎ© ўЕЎєЎ±ўБўСЎ© Ў®ўА f(x) = (x^2 - 1)/(x - 1) ЎєўЖЎѓўЕЎІ x вЙ† 1 ўИ f(1)=k. ўЕЎІ ўВўКўЕЎ© k ўДЎ™ўГўИўЖ ЎІўДЎѓЎІўДЎ© ўЕЎ≥Ў™ўЕЎ±Ў© ЎєўЖЎѓ x=1ЎЯ",
      "explanation_en": "Simplify: x^2-1=(x-1)(x+1). After canceling, the limit as xвЖТ1 is 1+1=2. So k must equal 2 for continuity.",
      "classify_categories_ar": [],
      "classify_items_en": [],
      "grade": 11,
      "matching_pairs_ar": [],
      "question_en": "Function f(x) = (x^2 - 1)/(x - 1) for x вЙ† 1 and f(1)=k. What value of k makes f continuous at x=1?",
      "classify_categories_en": [],
      "classify_items_ar": [],
      "options_ar": [
        "0",
        "1",
        "2",
        "-1"
      ],
      "id": "6a4a009c91ae4df21ea39689",
      "created_date": "2026-07-05T06:58:36.340000",
      "updated_date": "2026-07-05T06:58:36.340000",
      "created_by_id": "service_54c00eed-6486-4029-9a2e-cf5b715d0b73",
      "is_sample": false
    },
    {
      "ordering_items_ar": [],
      "question_type": "multiple_choice",
      "options_en": [
        "-4",
        "0",
        "4",
        "-8"
      ],
      "correct_answer": "0",
      "ordering_items_en": [],
      "topic_en": "Differentiation and Integration",
      "explanation_ar": "f'(x)=3x^2 -10x +4. Ў®ЎІўДЎ™ЎєўИўКЎґ x=2 ўЖЎ≠ЎµўД 3¬Ј4 -20 +4 =12 -20 +4 = -4.",
      "test_type": "adaptive",
      "difficulty": "medium",
      "topic_ar": "ЎІўДЎ™ўБЎІЎґўД ўИЎІўДЎ™ўГЎІўЕўД",
      "matching_pairs_en": [],
      "question_ar": "Ў•Ў∞ЎІ ўГЎІўЖЎ™ f(x)=x^3 - 5x^2 + 4xЎМ ўБўЕЎІ ўВўКўЕЎ© f'(2)ЎЯ",
      "explanation_en": "f'(x)=3x^2 -10x +4. Substitute x=2: 3¬Ј4 -10¬Ј2 +4 =12 -20 +4 = -4.",
      "classify_categories_ar": [],
      "classify_items_en": [],
      "grade": 11,
      "matching_pairs_ar": [],
      "question_en": "If f(x)=x^3 - 5x^2 + 4x, what is f'(2)?",
      "classify_categories_en": [],
      "classify_items_ar": [],
      "options_ar": [
        "-4",
        "0",
        "4",
        "-8"
      ],
      "id": "6a4a009c91ae4df21ea3968a",
      "created_date": "2026-07-05T06:58:36.340000",
      "updated_date": "2026-07-05T06:58:36.340000",
      "created_by_id": "service_54c00eed-6486-4029-9a2e-cf5b715d0b73",
      "is_sample": false
    },
    {
      "ordering_items_ar": [],
      "question_type": "multiple_choice",
      "options_en": [
        "1",
        "3",
        "1/3",
        "0"
      ],
      "correct_answer": "0",
      "ordering_items_en": [],
      "topic_en": "Differentiation and Integration",
      "explanation_ar": "вИЂ3x^2 dx = x^3. Ў™ўВўКўКўЕ ўЕўЖ 0 Ў•ўДўЙ1 ўКЎєЎЈўК 1^3 - 0 = 1.",
      "test_type": "adaptive",
      "difficulty": "medium",
      "topic_ar": "ЎІўДЎ™ўБЎІЎґўД ўИЎІўДЎ™ўГЎІўЕўД",
      "matching_pairs_en": [],
      "question_ar": "ўЕЎІ ўВўКўЕЎ© ЎІўДЎ™ўГЎІўЕўД ЎІўДўЕЎ≠ЎѓЎѓ вИЂ_{0}^{1} 3x^2 dxЎЯ",
      "explanation_en": "вИЂ3x^2 dx = x^3. Evaluated from 0 to 1 gives 1^3 - 0 = 1.",
      "classify_categories_ar": [],
      "classify_items_en": [],
      "grade": 11,
      "matching_pairs_ar": [],
      "question_en": "What is the value of the definite integral вИЂ_{0}^{1} 3x^2 dx?",
      "classify_categories_en": [],
      "classify_items_ar": [],
      "options_ar": [
        "1",
        "3",
        "1/3",
        "0"
      ],
      "id": "6a4a009c91ae4df21ea3968b",
      "created_date": "2026-07-05T06:58:36.340000",
      "updated_date": "2026-07-05T06:58:36.340000",
      "created_by_id": "service_54c00eed-6486-4029-9a2e-cf5b715d0b73",
      "is_sample": false
    },
    {
      "ordering_items_ar": [],
      "question_type": "multiple_choice",
      "options_en": [
        "2",
        "4",
        "8",
        "-4"
      ],
      "correct_answer": "1",
      "ordering_items_en": [],
      "topic_en": "Advanced Algebra",
      "explanation_ar": "ўДўИЎђўИЎѓ ЎђЎ∞Ў± ўЕўГЎ±Ў±: ЎІўДўЕўЕўКЎ≤ ќФ = b^2 - 4ac = 0. ўЗўЖЎІ 16 - 4k = 0 вЗТ k = 4.",
      "test_type": "adaptive",
      "difficulty": "medium",
      "topic_ar": "ЎІўДЎђЎ®Ў± ЎІўДўЕЎ™ўВЎѓўЕ",
      "matching_pairs_en": [],
      "question_ar": "ўВўКўЕЎ© ЎІўДЎЂЎІЎ®Ў™ k Ў®Ў≠ўКЎЂ ўКўГўИўЖ ўДўДўЕЎєЎІЎѓўДЎ© x^2 + 4x + k = 0 ЎђЎ∞ўИЎ± ўЕўГЎ±Ў±Ў© ўЗўК:",
      "explanation_en": "For a repeated root, discriminant ќФ = b^2 - 4ac = 0. Here 16 - 4k = 0 вЗТ k = 4.",
      "classify_categories_ar": [],
      "classify_items_en": [],
      "grade": 11,
      "matching_pairs_ar": [],
      "question_en": "The value of k so that x^2 + 4x + k = 0 has a repeated root is:",
      "classify_categories_en": [],
      "classify_items_ar": [],
      "options_ar": [
        "2",
        "4",
        "8",
        "-4"
      ],
      "id": "6a4a009c91ae4df21ea3968c",
      "created_date": "2026-07-05T06:58:36.340000",
      "updated_date": "2026-07-05T06:58:36.340000",
      "created_by_id": "service_54c00eed-6486-4029-9a2e-cf5b715d0b73",
      "is_sample": false
    },
    {
      "ordering_items_ar": [],
      "question_type": "multiple_choice",
      "options_en": [
        "{-2, 2}",
        "{0}",
        "{2}",
        "{-2}"
      ],
      "correct_answer": "0",
      "ordering_items_en": [],
      "topic_en": "Advanced Algebra",
      "explanation_ar": "ўЖўВЎ≥ўЕ Ў•ўДўЙ Ў≠ЎІўДЎІЎ™: Ў•Ў∞ЎІ xвЙ•1 вЗТ 2x=4 вЗТ x=2. Ў•Ў∞ЎІ xвЙ§-1 вЗТ -2x=4 вЗТ x=-2. ЎІўДЎ≠ЎІўДЎ© ЎІўДўИЎ≥ЎЈўЙ ўДЎІ Ў™ўПЎєЎЈўК Ў≠ўДўЛЎІ. Ў•Ў∞ўЛЎІ ЎІўДЎ≠ўДЎІўЖ -2 ўИ2.",
      "test_type": "adaptive",
      "difficulty": "medium",
      "topic_ar": "ЎІўДЎђЎ®Ў± ЎІўДўЕЎ™ўВЎѓўЕ",
      "matching_pairs_en": [],
      "question_ar": "Ў≠ўД ЎІўДўЕЎєЎІЎѓўДЎ© |x-1| + |x+1| = 4 Ў®ЎІўДўЖЎ≥Ў®Ў© ўДўДЎ£ЎєЎѓЎІЎѓ ЎІўДЎ≠ўВўКўВўКЎ© ўЗўИ:",
      "explanation_en": "Consider cases: xвЙ•1 вЗТ (x-1)+(x+1)=2x=4 вЗТ x=2. xвЙ§-1 вЗТ (1-x)+(-x-1)=-2x=4 вЗТ x=-2. Middle interval gives no solution. So x = -2, 2.",
      "classify_categories_ar": [],
      "classify_items_en": [],
      "grade": 11,
      "matching_pairs_ar": [],
      "question_en": "Solve |x-1| + |x+1| = 4 for real x:",
      "classify_categories_en": [],
      "classify_items_ar": [],
      "options_ar": [
        "{-2, 2}",
        "{0}",
        "{2}",
        "{-2}"
      ],
      "id": "6a4a009c91ae4df21ea3968d",
      "created_date": "2026-07-05T06:58:36.340000",
      "updated_date": "2026-07-05T06:58:36.340000",
      "created_by_id": "service_54c00eed-6486-4029-9a2e-cf5b715d0b73",
      "is_sample": false
    },
    {
      "ordering_items_ar": [],
      "question_type": "multiple_choice",
      "options_en": [
        "35 m",
        "40 m",
        "20 m",
        "17.5 m"
      ],
      "correct_answer": "0",
      "ordering_items_en": [],
      "topic_en": "Vectors and Projectiles",
      "explanation_ar": "ЎІўДўЕЎѓўЙ R = v^2 sin(2ќЄ)/g = 400¬Јsin60¬∞/9.8 вЙИ400¬Ј0.866/9.8 вЙИ346.4/9.8 вЙИ35.4 m вЖТ Ў™ўВЎ±ўКЎ®ўЛЎІ 35 m.",
      "test_type": "adaptive",
      "difficulty": "medium",
      "topic_ar": "ЎІўДўЕЎ™ЎђўЗЎІЎ™ ўИЎІўДўЕўВЎ∞ўИўБЎІЎ™",
      "matching_pairs_en": [],
      "question_ar": "Ў±ЎµЎІЎµЎ© Ў™ўПЎЈўДўВ Ў®Ў≥Ў±ЎєЎ© ЎІЎ®Ў™ЎѓЎІЎ¶ўКЎ© 20 m/s Ў®Ў≤ЎІўИўКЎ© 30¬∞ ўБўИўВ ЎІўДЎ£ўБўВўК. Ў™ўВЎ±ўКЎ®ўЛЎІ ўЕЎІ ўЕЎѓўЙ ЎІўДўЕўВЎ∞ўИўБ (ўЕЎє ЎІўБЎ™Ў±ЎІЎґ g=9.8 m/s^2)ЎЯ",
      "explanation_en": "Range R = v^2 sin(2ќЄ)/g = 400¬Јsin60¬∞/9.8 вЙИ400¬Ј0.866/9.8 вЙИ35.4 m, so about 35 m.",
      "classify_categories_ar": [],
      "classify_items_en": [],
      "grade": 11,
      "matching_pairs_ar": [],
      "question_en": "A projectile is launched at 20 m/s at 30¬∞ above horizontal. Approximately what is its horizontal range? (Take g=9.8 m/s^2)",
      "classify_categories_en": [],
      "classify_items_ar": [],
      "options_ar": [
        "35 m",
        "40 m",
        "20 m",
        "17.5 m"
      ],
      "id": "6a4a009c91ae4df21ea3968e",
      "created_date": "2026-07-05T06:58:36.340000",
      "updated_date": "2026-07-05T06:58:36.340000",
      "created_by_id": "service_54c00eed-6486-4029-9a2e-cf5b715d0b73",
      "is_sample": false
    },
    {
      "ordering_items_ar": [],
      "question_type": "multiple_choice",
      "options_en": [
        "(3, 4)",
        "(4, 3)",
        "(-3, 4)",
        "(5, 0)"
      ],
      "correct_answer": "0",
      "ordering_items_en": [],
      "topic_en": "Vectors and Projectiles",
      "explanation_ar": "cos53¬∞вЙИ0.6 вЗТ xвЙИ5¬Ј0.6=3. sin53¬∞вЙИ0.8 вЗТ yвЙИ5¬Ј0.8=4. Ў•Ў∞ўЛЎІ (3,4).",
      "test_type": "adaptive",
      "difficulty": "medium",
      "topic_ar": "ЎІўДўЕЎ™ЎђўЗЎІЎ™ ўИЎІўДўЕўВЎ∞ўИўБЎІЎ™",
      "matching_pairs_en": [],
      "question_ar": "ўЕЎ™ЎђўЗ ЎЈўИўДўЗ 5 ўИЎ≠ЎѓЎІЎ™ ўКЎµўЖЎє Ў≤ЎІўИўКЎ© вЙИ53¬∞ ўЕЎє ЎІўДўЕЎ≠ўИЎ± x. ўЕЎІ ўЕўГўИўСўЖЎІЎ™ўЗ ЎІўДЎ™ўВЎ±ўКЎ®ўКЎ© (x,y)ЎЯ",
      "explanation_en": "cos53¬∞вЙИ0.6 вЖТ xвЙИ5¬Ј0.6=3. sin53¬∞вЙИ0.8 вЖТ yвЙИ5¬Ј0.8=4. So components вЙИ(3,4).",
      "classify_categories_ar": [],
      "classify_items_en": [],
      "grade": 11,
      "matching_pairs_ar": [],
      "question_en": "A vector of magnitude 5 makes an angle вЙИ53¬∞ with the x-axis. What are its approximate (x,y) components?",
      "classify_categories_en": [],
      "classify_items_ar": [],
      "options_ar": [
        "(3, 4)",
        "(4, 3)",
        "(-3, 4)",
        "(5, 0)"
      ],
      "id": "6a4a009c91ae4df21ea3968f",
      "created_date": "2026-07-05T06:58:36.340000",
      "updated_date": "2026-07-05T06:58:36.340000",
      "created_by_id": "service_54c00eed-6486-4029-9a2e-cf5b715d0b73",
      "is_sample": false
    },
    {
      "ordering_items_ar": [],
      "question_type": "multiple_choice",
      "options_en": [
        "H-F",
        "H-Cl",
        "H-Br",
        "H-I"
      ],
      "correct_answer": "0",
      "ordering_items_en": [],
      "topic_en": "Molecular Chemistry",
      "explanation_ar": "ЎІўДўВЎЈЎ®ўКЎ© Ў™ЎєЎ™ўЕЎѓ ЎєўДўЙ ўБЎ±ўВ ЎІўДўГўЗЎ±ўИЎ≥ЎІўДЎ®ўКЎ©. ЎІўДўБўДўИЎ± ўДўЗ Ў£ЎєўДўЙ ўГўЗЎ±ўИЎ≥ЎІўДЎ®ўКЎ©ЎМ ўДЎ∞ўДўГ H-F Ў£ўГЎЂЎ± ўВЎЈЎ®ўКЎ©.",
      "test_type": "adaptive",
      "difficulty": "medium",
      "topic_ar": "ЎІўДўГўКўЕўКЎІЎ° ЎІўДЎђЎ≤ўКЎ¶ўКЎ©",
      "matching_pairs_en": [],
      "question_ar": "Ў£ўК ўЕўЖ ЎІўДЎ±ўИЎІЎ®ЎЈ ЎІўДЎ™ЎІўДўКЎ© ўЗўК ЎІўДЎ£ўГЎЂЎ± ўВЎЈЎ®ўКЎ©ЎЯ H-F, H-Cl, H-Br, H-I",
      "explanation_en": "Polarity depends on electronegativity difference. Fluorine is the most electronegative, so HвАУF is the most polar.",
      "classify_categories_ar": [],
      "classify_items_en": [],
      "grade": 11,
      "matching_pairs_ar": [],
      "question_en": "Which of the following bonds is most polar? H-F, H-Cl, H-Br, H-I",
      "classify_categories_en": [],
      "classify_items_ar": [],
      "options_ar": [
        "H-F",
        "H-Cl",
        "H-Br",
        "H-I"
      ],
      "id": "6a4a009c91ae4df21ea39690",
      "created_date": "2026-07-05T06:58:36.340000",
      "updated_date": "2026-07-05T06:58:36.340000",
      "created_by_id": "service_54c00eed-6486-4029-9a2e-cf5b715d0b73",
      "is_sample": false
    },
    {
      "ordering_items_ar": [],
      "question_type": "multiple_choice",
      "options_en": [
        "NH3",
        "CH4",
        "CO2",
        "H2S"
      ],
      "correct_answer": "0",
      "ordering_items_en": [],
      "topic_en": "Molecular Chemistry",
      "explanation_ar": "ЎІўДЎ±ўИЎІЎ®ЎЈ ЎІўДўЗўКЎѓЎ±ўИЎђўКўЖўКЎ© Ў™Ў™ЎЈўДЎ® Ў∞Ў±Ў© ўЗўКЎѓЎ±ўИЎђўКўЖ ўЕЎ±Ў®ўИЎЈЎ© ўДЎ∞Ў±Ў© ЎєЎІўДўКЎ© ЎІўДўГўЗЎ±ўИЎ≥ЎІўДЎ®ўКЎ© ўЕЎЂўД N Ў£ўИ O Ў£ўИ F. NH3 ўКўДЎ®ўК ўЗЎ∞ЎІ ЎІўДЎіЎ±ЎЈ.",
      "test_type": "adaptive",
      "difficulty": "medium",
      "topic_ar": "ЎІўДўГўКўЕўКЎІЎ° ЎІўДЎђЎ≤ўКЎ¶ўКЎ©",
      "matching_pairs_en": [],
      "question_ar": "Ў£ўК ЎІўДЎђЎ≤ўКЎ¶ЎІЎ™ ЎІўДЎ™ЎІўДўКЎ© ўКўЕўГўЖўЗ Ў™ўГўИўКўЖ Ў±ўИЎІЎ®ЎЈ ўЗўКЎѓЎ±ўИЎђўКўЖўКЎ© Ў®ЎіўГўД ўИЎІЎґЎ≠ЎЯ NH3, CH4, CO2, H2S",
      "explanation_en": "Hydrogen bonding requires H bonded to highly electronegative N, O, or F. NH3 has NвАУH bonds and can participate in hydrogen bonding.",
      "classify_categories_ar": [],
      "classify_items_en": [],
      "grade": 11,
      "matching_pairs_ar": [],
      "question_en": "Which of the following molecules can form clear hydrogen bonds? NH3, CH4, CO2, H2S",
      "classify_categories_en": [],
      "classify_items_ar": [],
      "options_ar": [
        "NH3",
        "CH4",
        "CO2",
        "H2S"
      ],
      "id": "6a4a009c91ae4df21ea39691",
      "created_date": "2026-07-05T06:58:36.340000",
      "updated_date": "2026-07-05T06:58:36.340000",
      "created_by_id": "service_54c00eed-6486-4029-9a2e-cf5b715d0b73",
      "is_sample": false
    },
    {
      "ordering_items_ar": [],
      "question_type": "multiple_choice",
      "options_en": [
        "1/2",
        "1/4",
        "3/4",
        "1"
      ],
      "correct_answer": "1",
      "ordering_items_en": [],
      "topic_en": "Genetics and Genes",
      "explanation_ar": "ЎђЎѓўИўД Ў®ўИўЖЎ™: ЎІўДЎ™ўИўДўКўБЎІЎ™ AA, Aa, aA, aa вЗТ ўИЎІЎ≠Ўѓ ўЕўЖ Ў£Ў±Ў®ЎєЎ© ўЗўИ aaЎМ ўДЎ∞ЎІ ЎІўДЎІЎ≠Ў™ўЕЎІўД 1/4.",
      "test_type": "adaptive",
      "difficulty": "medium",
      "topic_ar": "ЎІўДўИЎ±ЎІЎЂЎ© ўИЎІўДЎђўКўЖЎІЎ™",
      "matching_pairs_en": [],
      "question_ar": "Ў•Ў∞ЎІ ўГЎІўЖ ўДЎѓўЙ ЎІўДЎ£Ў®ўИўКўЖ Ў™Ў±ўГўКЎ® ЎђўКўЖўК Aa √Ч Aa ўДЎµўБЎ© ўЕЎ™ўЖЎ≠ўКЎ© (ЎІўДЎ±ўЕЎ≤ a)ЎМ ўЕЎІ ЎІЎ≠Ў™ўЕЎІўД Ў£ўЖ ўКўГўИўЖ ЎІўДўЖЎ≥ўД aa ЎЄЎІўЗЎ±ўКўЛЎІ (ўКЎєЎ®Ў± ЎєўЖ ЎІўДЎµўБЎ© ЎІўДўЕЎ™ўЖЎ≠ўКЎ©)ЎЯ",
      "explanation_en": "Punnett square gives genotypes AA, Aa, aA, aa. One out of four is aa, so probability = 1/4.",
      "classify_categories_ar": [],
      "classify_items_en": [],
      "grade": 11,
      "matching_pairs_ar": [],
      "question_en": "If parents are Aa √Ч Aa for a trait with recessive allele a, what is the probability their child is aa (shows the recessive trait)?",
      "classify_categories_en": [],
      "classify_items_ar": [],
      "options_ar": [
        "1/2",
        "1/4",
        "3/4",
        "1"
      ],
      "id": "6a4a009c91ae4df21ea39692",
      "created_date": "2026-07-05T06:58:36.340000",
      "updated_date": "2026-07-05T06:58:36.340000",
      "created_by_id": "service_54c00eed-6486-4029-9a2e-cf5b715d0b73",
      "is_sample": false
    },
    {
      "ordering_items_ar": [],
      "question_type": "multiple_choice",
      "options_en": [
        "1/4",
        "1/2",
        "3/4",
        "0"
      ],
      "correct_answer": "1",
      "ordering_items_en": [],
      "topic_en": "Genetics and Genes",
      "explanation_ar": "ўЕўЖ Ў™ўВЎІЎЈЎє Aa √Ч aa ўЖЎ≠ЎµўД Aa ўИ aa Ў®ўЖЎ≥Ў® 1/2 ўИ1/2ЎМ ўБЎІЎ≠Ў™ўЕЎІўД Ў≠ЎµўИўД ЎЈўБўД ўЕЎ™Ў£ЎЂЎ± (ўКЎ≠ўЕўД A) = 1/2.",
      "test_type": "adaptive",
      "difficulty": "medium",
      "topic_ar": "ЎІўДўИЎ±ЎІЎЂЎ© ўИЎІўДЎђўКўЖЎІЎ™",
      "matching_pairs_en": [],
      "question_ar": "ЎµўБЎ© Ў≥ЎІЎ¶ЎѓЎ© ЎђЎ≥ўЕЎІўЖўКЎ© (A). Ў£Ў≠Ўѓ ЎІўДЎ£Ў®ўИўКўЖ ўЕЎ™Ў£ЎЂЎ± ўИЎ±ЎІЎЂўКўЛЎІ ўИЎ™Ў±ўГўКЎ®ўПўЗ AaЎМ ўИЎІўДЎҐЎЃЎ± aa. ўЕЎІ ЎІЎ≠Ў™ўЕЎІўД Ў£ўЖ ўКўГўИўЖ ЎІўДЎЈўБўД ўЕЎ™Ў£ЎЂЎ±ўЛЎІЎЯ",
      "explanation_en": "Cross Aa √Ч aa yields offspring Aa and aa equally (1/2 each). So probability child is affected (has A) = 1/2.",
      "classify_categories_ar": [],
      "classify_items_en": [],
      "grade": 11,
      "matching_pairs_ar": [],
      "question_en": "A trait is autosomal dominant (A). One parent is affected heterozygous Aa, the other is aa. What is the probability a child is affected?",
      "classify_categories_en": [],
      "classify_items_ar": [],
      "options_ar": [
        "1/4",
        "1/2",
        "3/4",
        "0"
      ],
      "id": "6a4a009c91ae4df21ea39693",
      "created_date": "2026-07-05T06:58:36.340000",
      "updated_date": "2026-07-05T06:58:36.340000",
      "created_by_id": "service_54c00eed-6486-4029-9a2e-cf5b715d0b73",
      "is_sample": false
    },
    {
      "ordering_items_ar": [],
      "question_type": "multiple_choice",
      "options_en": [
        "Renewable energy is beneficial because it reduces emissions and supports sustainability",
        "Fossil fuels are cheaper than renewable energy",
        "Solar energy is ineffective",
        "Local energy projects should be stopped"
      ],
      "correct_answer": "0",
      "ordering_items_en": [],
      "topic_en": "Reading Comprehension",
      "explanation_ar": "ЎІўДўЕўВЎЈЎє ўКЎ∞ўГЎ± ўБўИЎІЎ¶Ўѓ ЎІўДЎЈЎІўВЎ© ЎІўДўЕЎ™ЎђЎѓЎѓЎ©: Ў™ўВўДўКўД ЎІўДЎІЎєЎ™ўЕЎІЎѓ ЎєўДўЙ ЎІўДўИўВўИЎѓ ЎІўДЎ£Ў≠ўБўИЎ±ўКЎМ ЎЃўБЎґ ЎІўДЎІўЖЎ®ЎєЎІЎЂЎІЎ™ЎМ ўИЎѓЎєўЕ ЎІўДЎІЎ≥Ў™ЎѓЎІўЕЎ© ЎІўДўЕЎ≠ўДўКЎ©ЎМ ўИўЗўК ЎІўДўБўГЎ±Ў© ЎІўДЎ£Ў≥ЎІЎ≥ўКЎ©.",
      "test_type": "adaptive",
      "difficulty": "medium",
      "topic_ar": "ЎІўДЎІЎ≥Ў™ўКЎєЎІЎ® ЎІўДўЖўВЎѓўК",
      "matching_pairs_en": [],
      "question_ar": "ЎІўДўЕўВЎЈЎє: \"Ў™ўПЎєЎѓ ўЕЎµЎІЎѓЎ± ЎІўДЎЈЎІўВЎ© ЎІўДўЕЎ™ЎђЎѓЎѓЎ© ўЕЎЂўД ЎІўДЎ±ўКЎІЎ≠ ўИЎІўДЎЈЎІўВЎ© ЎІўДЎіўЕЎ≥ўКЎ© ўЕўЗўЕЎ© ўДЎ£ўЖўЗЎІ Ў™ўВўДўД ЎІўДЎІЎєЎ™ўЕЎІЎѓ ЎєўДўЙ ЎІўДўИўВўИЎѓ ЎІўДЎ£Ў≠ўБўИЎ±ўК ўИЎ™ЎЃўБЎґ ЎІўДЎІўЖЎ®ЎєЎІЎЂЎІЎ™ ЎІўДЎґЎІЎ±Ў©. ўГўЕЎІ Ў£ўЖўЗЎІ Ў™Ў≥ЎІўЗўЕ ўБўК Ў™ўИўБўКЎ± ЎЈЎІўВЎ© ўЕЎ≥Ў™ЎѓЎІўЕЎ© ўДўДўЕЎђЎ™ўЕЎєЎІЎ™ ЎІўДўЕЎ≠ўДўКЎ©.\" ўЕЎІ ЎІўДўБўГЎ±Ў© ЎІўДЎ£Ў≥ЎІЎ≥ўКЎ© ўДўДўЕўВЎЈЎєЎЯ",
      "explanation_en": "The passage lists benefits of renewable energyвАФreducing fossil fuel reliance, lowering emissions, and supporting local sustainabilityвАФwhich is the main idea.",
      "classify_categories_ar": [],
      "classify_items_en": [],
      "grade": 11,
      "matching_pairs_ar": [],
      "question_en": "Passage: \"Renewable energy sources like wind and solar are important because they reduce reliance on fossil fuels and lower harmful emissions. They also help provide sustainable energy for local communities.\" What is the main idea of the passage?",
      "classify_categories_en": [],
      "classify_items_ar": [],
      "options_ar": [
        "ЎІўДЎЈЎІўВЎ© ЎІўДўЕЎ™ЎђЎѓЎѓЎ© ўЕўБўКЎѓЎ© ўДЎ£ўЖўЗЎІ Ў™ўВўДўД ЎІўДЎІўЖЎ®ЎєЎІЎЂЎІЎ™ ўИЎ™ЎѓЎєўЕ ЎІўДЎІЎ≥Ў™ЎѓЎІўЕЎ©",
        "ЎІўДўИўВўИЎѓ ЎІўДЎ£Ў≠ўБўИЎ±ўК Ў£Ў±ЎЃЎµ ўЕўЖ ЎІўДЎЈЎІўВЎ© ЎІўДўЕЎ™ЎђЎѓЎѓЎ©",
        "ЎІўДЎЈЎІўВЎ© ЎІўДЎіўЕЎ≥ўКЎ© ЎЇўКЎ± ўБЎєЎІўДЎ©",
        "ўКЎђЎ® Ў•ўКўВЎІўБ ўЕЎіЎІЎ±ўКЎє ЎІўДЎЈЎІўВЎ© ЎІўДўЕЎ≠ўДўКЎ©"
      ],
      "id": "6a4a009c91ae4df21ea39694",
      "created_date": "2026-07-05T06:58:36.340000",
      "updated_date": "2026-07-05T06:58:36.340000",
      "created_by_id": "service_54c00eed-6486-4029-9a2e-cf5b715d0b73",
      "is_sample": false
    },
    {
      "ordering_items_ar": [],
      "question_type": "multiple_choice",
      "options_en": [
        "If the sun is shining then I will drink tea.",
        "If I drink tea then the sun is shining.",
        "If I don't drink tea then the sun is not shining.",
        "If the sun is not shining then I will not go for a walk."
      ],
      "correct_answer": "0",
      "ordering_items_en": [],
      "topic_en": "Logic and Reasoning",
      "explanation_ar": "ўЕўЖЎЈўВ ЎІўДЎ≥ўДЎ≥ўДЎ©: (sun вЖТ walk) ўИ (walk вЖТ tea) вЗТ (sun вЖТ tea) ЎєўЖ ЎЈЎ±ўКўВ ЎІўДўВўКЎІЎ≥ ЎІўДўЕЎ™ЎєЎѓўСўК (transitive implication).",
      "test_type": "adaptive",
      "difficulty": "medium",
      "topic_ar": "ЎІўДўЕўЖЎЈўВ ўИЎІўДЎІЎ≥Ў™ЎѓўДЎІўД",
      "matching_pairs_en": [],
      "question_ar": "ЎІўДўЕўВЎѓўЕЎІЎ™: \"Ў•Ў∞ЎІ ўГЎІўЖЎ™ ЎІўДЎіўЕЎ≥ ўЕЎіЎ±ўВЎ© ўБЎ≥Ў£Ў∞ўЗЎ® ўДўДўЕЎіўК.\" ўИ\"Ў•Ў∞ЎІ Ў∞ўЗЎ®Ў™ ўДўДўЕЎіўК ўБЎ≥Ў£ЎіЎ±Ў® ЎІўДЎіЎІўК.\" Ў£ўКўС ЎІўДЎІЎ≥Ў™ўЖЎ™ЎІЎђЎІЎ™ ЎІўДЎ™ЎІўДўКЎ© ЎµЎ≠ўКЎ≠ ўЕўЖЎЈўВўКўЛЎІЎЯ",
      "explanation_en": "By transitive implication: (sun вЖТ walk) and (walk вЖТ tea) together imply (sun вЖТ tea). The other options do not follow logically.",
      "classify_categories_ar": [],
      "classify_items_en": [],
      "grade": 11,
      "matching_pairs_ar": [],
      "question_en": "Premises: \"If the sun is shining then I will go for a walk.\" and \"If I go for a walk then I will drink tea.\" Which conclusion is logically valid?",
      "classify_categories_en": [],
      "classify_items_ar": [],
      "options_ar": [
        "Ў•Ў∞ЎІ ўГЎІўЖЎ™ ЎІўДЎіўЕЎ≥ ўЕЎіЎ±ўВЎ© ўБЎ≥Ў£ЎіЎ±Ў® ЎІўДЎіЎІўК.",
        "Ў•Ў∞ЎІ ЎіЎ±Ў®Ў™ ЎІўДЎіЎІўК ўБЎІўДЎіўЕЎ≥ ўЕЎіЎ±ўВЎ©.",
        "Ў•Ў∞ЎІ ўДўЕ Ў£ЎіЎ±Ў® ЎІўДЎіЎІўК ўБЎІўДЎіўЕЎ≥ ўДўКЎ≥Ў™ ўЕЎіЎ±ўВЎ©.",
        "Ў•Ў∞ЎІ ўДўЕ Ў™ўГўЖ ЎІўДЎіўЕЎ≥ ўЕЎіЎ±ўВЎ© ўБўДўЖ Ў£Ў∞ўЗЎ® ўДўДўЕЎіўК."
      ],
      "id": "6a4a009c91ae4df21ea39695",
      "created_date": "2026-07-05T06:58:36.340000",
      "updated_date": "2026-07-05T06:58:36.340000",
      "created_by_id": "service_54c00eed-6486-4029-9a2e-cf5b715d0b73",
      "is_sample": false
    },
    {
      "ordering_items_ar": [],
      "question_type": "multiple_choice",
      "options_en": [
        "0",
        "1",
        "2",
        "4"
      ],
      "correct_answer": "2",
      "ordering_items_en": [],
      "topic_en": "Functions and limits",
      "explanation_ar": "ЎІЎ≥Ў™ЎЃЎѓўЕ Ў™ўВЎ±ўКЎє Ў™ЎІўКўДўИЎ± Ў£ўИ ЎІўДўЗўИўКЎ© 1-cos u вЙИ u^2/2 ЎєўЖЎѓ u вЖТ 0. ўЗўЖЎІ u=2xЎМ Ў•Ў∞ўЖ ЎІўДЎ®Ў≥ЎЈ вЙИ (2x)^2/2 = 2x^2ЎМ ўИЎІўДўВЎ≥ўЕЎ© ЎєўДўЙ x^2 Ў™ЎєЎЈўК 2.",
      "test_type": "adaptive",
      "difficulty": "hard",
      "topic_ar": "ЎІўДЎѓўИЎІўД ўИЎІўДўЖўЗЎІўКЎІЎ™",
      "matching_pairs_en": [],
      "question_ar": "ЎІЎ≠Ў≥Ў® ЎІўДўЖўЗЎІўКЎ©: lim_{xвЖТ0} (1 - cos(2x)) / x^2",
      "explanation_en": "Use Taylor approximation or identity 1 - cos u вЙИ u^2/2 for uвЖТ0. Here u=2x so numerator вЙИ(2x)^2/2=2x^2; dividing by x^2 gives 2.",
      "classify_categories_ar": [],
      "classify_items_en": [],
      "grade": 11,
      "matching_pairs_ar": [],
      "question_en": "Compute the limit: lim_{xвЖТ0} (1 - cos(2x)) / x^2",
      "classify_categories_en": [],
      "classify_items_ar": [],
      "options_ar": [
        "0",
        "1",
        "2",
        "4"
      ],
      "id": "6a4a009c91ae4df21ea39696",
      "created_date": "2026-07-05T06:58:36.340000",
      "updated_date": "2026-07-05T06:58:36.340000",
      "created_by_id": "service_54c00eed-6486-4029-9a2e-cf5b715d0b73",
      "is_sample": false
    },
    {
      "ordering_items_ar": [],
      "question_type": "multiple_choice",
      "options_en": [
        "k = 1",
        "k = 2",
        "k = 0",
        "No such value"
      ],
      "correct_answer": "2",
      "ordering_items_en": [],
      "topic_en": "Functions and limits",
      "explanation_ar": "ЎіЎ±ЎЈ ЎІўДЎІЎ≥Ў™ўЕЎ±ЎІЎ±ўКЎ© ЎєўЖЎѓ x=2: lim ўЕўЖ ЎІўДўКЎ≥ЎІЎ± = lim ўЕўЖ ЎІўДўКўЕўКўЖ. ўЕўЖ ЎІўДўКЎ≥ЎІЎ± 2k+3ЎМ ўЕўЖ ЎІўДўКўЕўКўЖ 2^2-1=3. Ў•Ў∞ўЖ 2k+3=3 вЗТ k=0. ЎІўДўЕЎіЎ™ўВЎ© ўЕўЖ ЎІўДўКЎ≥ЎІЎ± = k =0ЎМ ўИўЕўЖ ЎІўДўКўЕўКўЖ = 2x ЎєўЖЎѓ 2 =4ЎЫ ЎЇўКЎ± ўЕЎ™Ў≥ЎІўИўКЎ™ўКўЖЎМ Ў•Ў∞ЎІўЛ ЎЇўКЎ± ўВЎІЎ®ўДЎ© ўДўДЎІЎіЎ™ўВЎІўВ. (Ў•Ў∞ўЖ k=0 ўКЎ≠ўВўВ ЎІўДЎіЎ±ЎЈ ЎІўДўЕЎЈўДўИЎ®.)",
      "test_type": "adaptive",
      "difficulty": "hard",
      "topic_ar": "ЎІўДЎѓўИЎІўД ўИЎІўДўЖўЗЎІўКЎІЎ™",
      "matching_pairs_en": [],
      "question_ar": "ўДЎѓўКўЖЎІ ЎІўДЎѓЎІўДЎ© ЎІўДўЕЎ≠ЎѓЎѓЎ© ЎђЎ≤Ў¶ўКЎІўЛ: f(x)= { kx+3 ЎІЎ∞ЎІ x<2 ; x^2-1 ЎІЎ∞ЎІ xвЙ•2 }. ўЕЎІ ўВўКўЕЎ© k Ў®Ў≠ўКЎЂ Ў™ўГўИўЖ f ўЕЎ≥Ў™ўЕЎ±Ў© ЎєўЖЎѓ x=2 ўИўДўГўЖўЗЎІ ўДўКЎ≥Ў™ ўВЎІЎ®ўДЎ© ўДўДЎІЎіЎ™ўВЎІўВ ЎєўЖЎѓ x=2ЎЯ",
      "explanation_en": "Continuity at x=2 requires left limit = right value. Left: 2k+3; right: 2^2-1=3 вЖТ 2k+3=3 вЗТ k=0. Left derivative = k =0; right derivative = 2x at x=2 =4, not equal, so not differentiable. Thus k=0 satisfies the requirement.",
      "classify_categories_ar": [],
      "classify_items_en": [],
      "grade": 11,
      "matching_pairs_ar": [],
      "question_en": "Consider the piecewise function f(x)= { kx+3 for x<2 ; x^2-1 for xвЙ•2 }. Find k so that f is continuous at x=2 but not differentiable at x=2.",
      "classify_categories_en": [],
      "classify_items_ar": [],
      "options_ar": [
        "k = 1",
        "k = 2",
        "k = 0",
        "ўДЎІ Ў™ўИЎђЎѓ ўВўКўЕЎ©"
      ],
      "id": "6a4a009c91ae4df21ea39697",
      "created_date": "2026-07-05T06:58:36.340000",
      "updated_date": "2026-07-05T06:58:36.340000",
      "created_by_id": "service_54c00eed-6486-4029-9a2e-cf5b715d0b73",
      "is_sample": false
    },
    {
      "ordering_items_ar": [],
      "question_type": "multiple_choice",
      "options_en": [
        "e^e",
        "2 e^{e}",
        "e^{e}(ln e + 1)",
        "0"
      ],
      "correct_answer": "1",
      "ordering_items_en": [],
      "topic_en": "Differentiation and integration",
      "explanation_ar": "d/dx x^x = x^x(ln x + 1). ЎєўЖЎѓ x=e ўЖЎ≠ЎµўД ЎєўДўЙ e^e(1 + 1) = 2 e^e. (ЎІўДЎЃўКЎІЎ± ЎІўДўЕЎЈЎІЎ®ўВ ўЗўИ ЎІўДЎЂЎІўЖўК Ў®ЎєЎѓ Ў™Ў±Ў™ўКЎ® ЎІўДЎЃўКЎІЎ±ЎІЎ™ ЎІўДЎєЎ±Ў®ўКЎ©/ЎІўДЎ•ўЖЎђўДўКЎ≤ўКЎ©ЎЫ ЎІўДўЕЎ§ЎіЎ± ўЗўЖЎІ ўКЎіўКЎ± Ў•ўДўЙ ЎІўДЎЃўКЎІЎ± Ў±ўВўЕ 1 Ў®ЎµўКЎЇЎ© ЎµўБЎ±ўКЎ©.)",
      "test_type": "adaptive",
      "difficulty": "hard",
      "topic_ar": "ЎІўДЎ™ўБЎІЎґўД ўИЎІўДЎ™ўГЎІўЕўД",
      "matching_pairs_en": [],
      "question_ar": "Ў•Ў∞ЎІ ўГЎІўЖЎ™ y = x^xЎМ ўБўЕЎІ ўВўКўЕЎ© dy/dx ЎєўЖЎѓ x = eЎЯ",
      "explanation_en": "d/dx x^x = x^x(ln x + 1). At x=e this is e^e(1+1)=2 e^e. (The correct listed option is the one giving 2 e^e.)",
      "classify_categories_ar": [],
      "classify_items_en": [],
      "grade": 11,
      "matching_pairs_ar": [],
      "question_en": "If y = x^x, what is dy/dx at x = e?",
      "classify_categories_en": [],
      "classify_items_ar": [],
      "options_ar": [
        "e^e",
        "2 e^{e}",
        "e^{e}(ln e + 1)",
        "0"
      ],
      "id": "6a4a009c91ae4df21ea39698",
      "created_date": "2026-07-05T06:58:36.340000",
      "updated_date": "2026-07-05T06:58:36.340000",
      "created_by_id": "service_54c00eed-6486-4029-9a2e-cf5b715d0b73",
      "is_sample": false
    },
    {
      "ordering_items_ar": [],
      "question_type": "multiple_choice",
      "options_en": [
        "(ln 2)",
        "(ln 2)^2",
        "1/2 (ln 2)^2",
        "1/4 (ln 2)^2"
      ],
      "correct_answer": "2",
      "ordering_items_en": [],
      "topic_en": "Differentiation and integration",
      "explanation_ar": "ЎґЎє u = ln(1+x) => du = dx/(1+x). ўКЎµЎ®Ў≠ ЎІўДЎ™ўГЎІўЕўД вИЂ_{u=0}^{u=ln2} u du = 1/2 u^2|_0^{ln2} = 1/2 (ln2)^2.",
      "test_type": "adaptive",
      "difficulty": "hard",
      "topic_ar": "ЎІўДЎ™ўБЎІЎґўД ўИЎІўДЎ™ўГЎІўЕўД",
      "matching_pairs_en": [],
      "question_ar": "ЎІЎ≠Ў≥Ў® ЎІўДЎ™ўГЎІўЕўД ЎІўДўЕЎ≠ЎѓЎѓ I = вИЂ_{0}^{1} ln(1+x)/(1+x) dx.",
      "explanation_en": "Let u = ln(1+x) вЗТ du = dx/(1+x). The integral becomes вИЂ_{0}^{ln2} u du = 1/2 u^2|_0^{ln2} = 1/2 (ln2)^2.",
      "classify_categories_ar": [],
      "classify_items_en": [],
      "grade": 11,
      "matching_pairs_ar": [],
      "question_en": "Compute the definite integral I = вИЂ_{0}^{1} ln(1+x)/(1+x) dx.",
      "classify_categories_en": [],
      "classify_items_ar": [],
      "options_ar": [
        "(ln 2)",
        "(ln 2)^2",
        "1/2 (ln 2)^2",
        "1/4 (ln 2)^2"
      ],
      "id": "6a4a009c91ae4df21ea39699",
      "created_date": "2026-07-05T06:58:36.340000",
      "updated_date": "2026-07-05T06:58:36.340000",
      "created_by_id": "service_54c00eed-6486-4029-9a2e-cf5b715d0b73",
      "is_sample": false
    },
    {
      "ordering_items_ar": [],
      "question_type": "multiple_choice",
      "options_en": [
        "For all real a",
        "When |a| < 2",
        "When |a| > 2",
        "Only when a = 0"
      ],
      "correct_answer": "1",
      "ordering_items_en": [],
      "topic_en": "Advanced algebra",
      "explanation_ar": "ўДўЖўГЎ™Ў® ЎІўДЎіўГўД x^3 + p x + q ўЕЎє p = -3ЎМ q = a. ЎІўДўЕўЕўКЎ≤ ќФ = -4p^3 -27q^2 = 108 - 27 a^2 = 27(4 - a^2). ўДўДўЕўЕўКЎ≤ ўЕўИЎђЎ® (ЎЂўДЎІЎЂЎ© ЎђЎ∞ўИЎ± Ў≠ўВўКўВўКЎ© ўЕЎЃЎ™ўДўБЎ©) ўКЎђЎ® Ў£ўЖ ўКўГўИўЖ 4 - a^2 > 0 вЗТ |a| < 2.",
      "test_type": "adaptive",
      "difficulty": "hard",
      "topic_ar": "ЎІўДЎђЎ®Ў± ЎІўДўЕЎ™ўВЎѓўЕ",
      "matching_pairs_en": [],
      "question_ar": "ўДўДўЕЎ™ЎЇўКЎ± ЎІўДЎ≠ўВўКўВўК aЎМ ўЕЎ™ўЙ ўКўГўИўЖ ўГЎЂўКЎ± ЎІўДЎ≠ЎѓўИЎѓ x^3 - 3x + a Ў∞ўИ ЎЂўДЎІЎЂЎ© ЎђЎ∞ўИЎ± Ў≠ўВўКўВўКЎ© ўЕЎЃЎ™ўДўБЎ©ЎЯ",
      "explanation_en": "Write as x^3 + p x + q with p=-3, q=a. Discriminant ќФ = -4 p^3 -27 q^2 = 108 -27 a^2 = 27(4 - a^2). ќФ>0 (three distinct real roots) вЗФ 4 - a^2 >0 вЗТ |a|<2.",
      "classify_categories_ar": [],
      "classify_items_en": [],
      "grade": 11,
      "matching_pairs_ar": [],
      "question_en": "For real parameter a, when does the polynomial x^3 - 3x + a have three distinct real roots?",
      "classify_categories_en": [],
      "classify_items_ar": [],
      "options_ar": [
        "ўДўГўД a вИИ вДЭ",
        "ЎєўЖЎѓўЕЎІ |a| < 2",
        "ЎєўЖЎѓўЕЎІ |a| > 2",
        "ЎєўЖЎѓўЕЎІ a = 0 ўБўВЎЈ"
      ],
      "id": "6a4a009c91ae4df21ea3969a",
      "created_date": "2026-07-05T06:58:36.340000",
      "updated_date": "2026-07-05T06:58:36.340000",
      "created_by_id": "service_54c00eed-6486-4029-9a2e-cf5b715d0b73",
      "is_sample": false
    }
  ]
}